Workbook

Sheet Итог
A1: Сверка ETM ↔ 1С ↔ реестр: итог
A2: Числа в первом блоке — формулы по листам отчёта.
A4: Субагентов в сверке | B4: =COUNTA('По субагентам'!A5:A104)
A5: Суммарный разрыв (сальдо 1С + баланс ETM) на конец периода, KGS | B5: ='По субагентам'!C105
A6: Рекомендуется сдвинуть баланс ETM (нетто), KGS | B6: ='По субагентам'!D105
A7: Рекомендуется исправить в 1С (нетто), KGS | B7: ='По субагентам'!E105
A8: Нужно выяснить (нетто), KGS | B8: ='По субагентам'!F105
A9: Остаток разрыва после правок (=выяснить + округления), KGS | B9: ='По субагентам'!K105
A10: Не объяснено мостом: сумма по 100 субагентам, KGS | B10: =SUM('Мост'!W4:W103)
A12: Что нашли (факты по данным)
A13: Сумма модулей: сдвиг баланса ETM по субагентам, KGS | B13: 55163943
A14: Сумма модулей: правки в 1С по субагентам, KGS | B14: 12258753
A15: Сумма модулей: «сначала выяснить» по субагентам, KGS | B15: 38343106
A16: Операций ETM / строк 1С (последние версии актов) / строк реестра | B16: 25,237 / 18,711 / 12,146
A17: Групп билетов (заказов) всего | B17: 15499
A18: Групп, присутствующих и в ETM, и в 1С | B18: 13585
A19: …из них сошлись до 5 KGS | B19: 94.1%
A20: Группы с неверной суммой | B20: 758
A21: …подтверждено реестром как ошибка 1С (A) | B21: 195
A22: …подтверждено реестром как ошибка бота (A) | B22: 200
A23: …похоже на опечатку цифр в 1С (гипотеза, B) | B23: 29
A24: …источник не установить без бухгалтера (C) | B24: 334
A25: Двойных списаний бота | B25: 40
A26: Продажи реестра и 1С, которые бот не перенёс в ETM | B26: 83
A27: Операции ETM без реализации в 1С (акт за месяц есть) | B27: 243
A28: Операции ETM, где акт 1С за месяц не выгружен | B28: 487
A29: Поступления 1С без оплаты в ETM | B29: 221
A30: …их сумма, KGS (главный по величине источник разрыва) | B30: 60646400
A31: Повторные зачисления оплат в ETM | B31: 25
... A38: Разрывов цепочки баланса ETM (по субагенту; одинаковая секунда) | B38: 6
A40: Честные оговорки
A41: • Это кандидаты с источником и уверенностью, а не «N ошибок»: A — подтверждено вторым источником, B — гипотеза, C — данных недостаточно.
A42: • Источник нельзя установить для 334 расхождений в сумме: у билетов, выписанных самим субагентом, нет записи в реестре — третьего голоса нет.
A43: • Мост построен без заплаток: каждая строка 1С и ETM попала ровно в одну колонку, «не объяснено» — формула и равна нулю; но колонки «выяснить» (начальный разрыв, недостающие акты) — честно нераспределённые суммы.
A44: • Итоги «нетто» скрывают взаимное погашение разных знаков — рядом показаны суммы модулей по субагентам.
A45: • ETM balance_after — сквозной баланс субагента, а не договора: цепочка проверяется по субагенту.
A46: • ML размечен правилами (слабая разметка) и работает как приоритизатор; его качество показано рядом с baseline и скромное.

Sheet По субагентам
A1: Отчёт по каждому субагенту: что двигать, что исправлять, что выяснить
A2: Разрыв = сальдо 1С + баланс ETM (идеал 0). Корректировки закрывают найденные расхождения; то, что данные объяснить не могут, вынесено в «Выяснить», а не растворено в остатке.
A4: Субагент | B4: Разрыв на начало периода | C4: Разрыв на конец (сальдо 1С + баланс ETM) | D4: Сдвинуть баланс ETM на, KGS | E4: Исправить в 1С на, KGS | F4: Сначала выяснить, KGS | G4: Округления групп, KGS | H4: Рекомендация | I4: Проблемных групп и платежей | J4: Месяцев без акта 1С | K4: Остаток после правок, KGS (=C+D+E) | L4: Проверка: остаток − выяснить − округление − необъяснённое (≈0)
A5: SkyWay Travel | B5: 0 | C5: -8740000 | D5: 7406401.6 | E5: 1306266.3 | F5: -27327.17 | G5: -4.91 | H5: Сдвинуть баланс ETM на +7,406,401.59 (дубль списания: 6; бот не перенёс продажу: 8; повторная оплата: 1; оплата не зачислена: 22); Исправить 1С на +1,306,266.33 (не выставлено в 1С: 29); Сначала выяснить -27,327.17 (начальный разрыв, недостающие акты, спорные суммы) | I5: 156 | J5: 0 | K5: =C5+D5+E5 | L5: =ROUND(K5-F5-G5-(-0.000000002),2)
A6: ИП Токтосун кызы Н. | B6: 3674160.7 | C6: 2741200.5 | D6: 967849.87 | E6: -109475.16 | F6: 3599573.9 | G6: 1.3 | H6: Сдвинуть баланс ETM на +967,849.87 (дубль списания: 1; оплата не зачислена: 4); Исправить 1С на -109,475.16 (не выставлено в 1С: 1; оплата не проведена: 1); Сначала выяснить +3,599,573.86 (начальный разрыв, недостающие акты, спорные суммы) | I6: 47 | J6: 1 | K6: =C6+D6+E6 | L6: =ROUND(K6-F6-G6-(0.000000001),2)
A7: Джолдош уулу Руслан | B7: -3723651.6 | C7: -4467449.9 | D7: 733276.9 | E7: 10000 | F7: -3724173 | G7: 0 | H7: Сдвинуть баланс ETM на +733,276.90 (дубль списания: 1; оплата не зачислена: 1); Исправить 1С на +10,000.00; Сначала выяснить -3,724,172.96 (начальный разрыв, недостающие акты, спорные суммы) | I7: 5 | J7: 0 | K7: =C7+D7+E7 | L7: =ROUND(K7-F7-G7-(-0.000000001),2)
A8: Steppe Travel | B8: 3309463.7 | C8: 2374699.1 | D8: 820246.08 | E8: 114481.21 | F8: 3309426.4 | G8: -7.2759576e-12 | H8: Сдвинуть баланс ETM на +820,246.08 (дубль списания: 1; бот не перенёс продажу: 1; оплата не зачислена: 2); Исправить 1С на +114,481.21 (не выставлено в 1С: 3); Сначала выяснить +3,309,426.35 (начальный разрыв, недостающие акты, спорные суммы) | I8: 10 | J8: 0 | K8: =C8+D8+E8 | L8: =ROUND(K8-F8-G8-(0.000000000),2)
A9: ОсОО Ала-Арча Авиа | B9: 3582785.7 | C9: 3072665.4 | D9: 424333.4 | E9: 88040.15 | F9: 3585038.9 | G9: 2.910383e-11 | H9: Сдвинуть баланс ETM на +424,333.40 (бот не перенёс продажу: 1; оплата не зачислена: 2); Исправить 1С на +88,040.15 (не выставлено в 1С: 2); Сначала выяснить +3,585,038.94 (начальный разрыв, недостающие акты, спорные суммы) | I9: 9 | J9: 0 | K9: =C9+D9+E9 | L9: =ROUND(K9-F9-G9-(0.000000000),2)
A10: Karakol Express | B10: 23846.3 | C10: -3899769.5 | D10: 3573418.1 | E10: 376207.84 | F10: 49861.13 | G10: -4.65 | H10: Сдвинуть баланс ETM на +3,573,418.13 (дубль списания: 2; бот не перенёс продажу: 6; повторная оплата: 3; оплата не зачислена: 21); Исправить 1С на +376,207.84 (не выставлено в 1С: 19); Сначала выяснить +49,861.13 (начальный разрыв, недостающие акты, спорные суммы) | I10: 112 | J10: 0 | K10: =C10+D10+E10 | L10: =ROUND(K10-F10-G10-(0.000000000),2)
A11: ОсОО Тянь-Шань Вояж | B11: -3914150.6 | C11: -3913364.4 | D11: 18213.79 | E11: -19000 | F11: -3914150.6 | G11: 7.2759576e-12 | H11: Сдвинуть баланс ETM на +18,213.79; Исправить 1С на -19,000.00; Сначала выяснить -3,914,150.59 (начальный разрыв, недостающие акты, спорные суммы) | I11: 4 | J11: 0 | K11: =C11+D11+E11 | L11: =ROUND(K11-F11-G11-(0.000000000),2)
A12: Ala-Too Travel | B12: -3233430.5 | C12: -3317307.5 | D12: 0 | E12: 83859.22 | F12: -3233448.3 | G12: -1.4551915e-11 | H12: Исправить 1С на +83,859.22 (не выставлено в 1С: 2); Сначала выяснить -3,233,448.31 (начальный разрыв, недостающие акты, спорные суммы) | I12: 4 | J12: 0 | K12: =C12+D12+E12 | L12: =ROUND(K12-F12-G12-(0.000000000),2)
A13: МУРАС ТРИП | B13: -2130878.8 | C13: -3218410.2 | D13: 919294.65 | E13: 158484.24 | F13: -2140631.3 | G13: 1.4551915e-11 | H13: Сдвинуть баланс ETM на +919,294.65 (дубль списания: 1; оплата не зачислена: 4); Исправить 1С на +158,484.24 (не выставлено в 1С: 1); Сначала выяснить -2,140,631.32 (начальный разрыв, недостающие акты, спорные суммы) | I13: 30 | J13: 1 | K13: =C13+D13+E13 | L13: =ROUND(K13-F13-G13-(0.000000000),2)
A14: Сатар уулу Санжар | B14: 3273224.4 | C14: 1019008 | D14: 1068778.6 | E14: -184864.77 | F14: 1902926.2 | G14: -4.4 | H14: Сдвинуть баланс ETM на +1,068,778.64 (дубль списания: 1; бот не перенёс продажу: 2; повторная оплата: 1; оплата не зачислена: 7; оплата не тому субагенту: 1); Исправить 1С на -184,864.77 (не выставлено в 1С: 3); Сначала выяснить +1,902,926.24 (начальный разрыв, недостающие акты, спорные суммы) | I14: 186 | J14: 2 | K14: =C14+D14+E14 | L14: =ROUND(K14-F14-G14-(0.000000002),2)
A15: Салам Экспресс | B15: 2800828.5 | C15: 2767104.1 | D15: -26797.3 | E15: 60699.21 | F15: 2801006 | G15: -7.2759576e-12 | H15: Сдвинуть баланс ETM на -26,797.30 (повторная оплата: 1; оплата не зачислена: 1); Исправить 1С на +60,699.21 (не выставлено в 1С: 2); Сначала выяснить +2,801,005.98 (начальный разрыв, недостающие акты, спорные суммы) | I15: 10 | J15: 0 | K15: =C15+D15+E15 | L15: =ROUND(K15-F15-G15-(0.000000000),2)
A16: Манас Тревел | B16: 1737199.2 | C16: 727989.01 | D16: 489305.26 | E16: 521531.47 | F16: 1738825.8 | G16: -0.05 | H16: Сдвинуть баланс ETM на +489,305.26 (бот не перенёс продажу: 4; оплата не зачислена: 3); Исправить 1С на +521,531.47 (не выставлено в 1С: 7); Сначала выяснить +1,738,825.79 (начальный разрыв, недостающие акты, спорные суммы) | I16: 34 | J16: 0 | K16: =C16+D16+E16 | L16: =ROUND(K16-F16-G16-(0.000000000),2)
A17: Джолдошова Салтанат Сатаревна | B17: -703393.53 | C17: -2501581.6 | D17: 1333859.7 | E17: 476089.01 | F17: -691632.85 | G17: -1.4551915e-11 | H17: Сдвинуть баланс ETM на +1,333,859.73 (дубль списания: 1; бот не перенёс продажу: 3; оплата не зачислена: 8); Исправить 1С на +476,089.01 (не выставлено в 1С: 13); Сначала выяснить -691,632.85 (начальный разрыв, недостающие акты, спорные суммы) | I17: 43 | J17: 0 | K17: =C17+D17+E17 | L17: =ROUND(K17-F17-G17-(0.000000000),2)
A18: Ак-Куу Авиа | B18: 453547.35 | C18: -1147683.2 | D18: 1248601.8 | E18: 338266.78 | F18: 439192.17 | G18: -6.77 | H18: Сдвинуть баланс ETM на +1,248,601.82 (дубль списания: 2; бот не перенёс продажу: 5; повторная оплата: 1; оплата не зачислена: 5); Исправить 1С на +338,266.78 (не выставлено в 1С: 14); Сначала выяснить +439,192.17 (начальный разрыв, недостающие акты, спорные суммы) | I18: 76 | J18: 0 | K18: =C18+D18+E18 | L18: =ROUND(K18-F18-G18-(-0.000000001),2)
A19: ИССЫК ТРИП | B19: 0 | C19: -1979507.3 | D19: 1067908.8 | E19: 365663.13 | F19: -545934.4 | G19: -0.95 | H19: Сдвинуть баланс ETM на +1,067,908.82 (дубль списания: 1; бот не перенёс продажу: 5; повторная оплата: 1; оплата не зачислена: 5); Исправить 1С на +365,663.13 (не выставлено в 1С: 4); Сначала выяснить -545,934.40 (начальный разрыв, недостающие акты, спорные суммы) | I19: 104 | J19: 1 | K19: =C19+D19+E19 | L19: =ROUND(K19-F19-G19-(0.000000000),2)
A20: Кадырова Айнура Жумабекевна | B20: 0 | C20: -1954142.9 | D20: 1692737.7 | E20: 261566.36 | F20: 160.68 | G20: 0.5 | H20: Сдвинуть баланс ETM на +1,692,737.73 (бот не перенёс продажу: 3; оплата не зачислена: 6); Исправить 1С на +261,566.36 (не выставлено в 1С: 7); Сначала выяснить +160.68 (начальный разрыв, недостающие акты, спорные суммы) | I20: 24 | J20: 0 | K20: =C20+D20+E20 | L20: =ROUND(K20-F20-G20-(0.000000001),2)
A21: ЧОЛПОН ТУР | B21: -404589.84 | C21: -1727139.1 | D21: 961494.6 | E21: 45627.75 | F21: -720016.73 | G21: 0 | H21: Сдвинуть баланс ETM на +961,494.60 (бот не перенёс продажу: 1; оплата не зачислена: 4); Исправить 1С на +45,627.75; Сначала выяснить -720,016.73 (начальный разрыв, недостающие акты, спорные суммы) | I21: 50 | J21: 2 | K21: =C21+D21+E21 | L21: =ROUND(K21-F21-G21-(0.000000000),2)
A22: Ыйык Тур | B22: 17858.87 | C22: -1667561.3 | D22: 1514597.3 | E22: 171945.45 | F22: 18981.39 | G22: 2.1827873e-11 | H22: Сдвинуть баланс ETM на +1,514,597.28 (дубль списания: 1; бот не перенёс продажу: 2; повторная оплата: 2; оплата не зачислена: 7); Исправить 1С на +171,945.45 (не выставлено в 1С: 3); Сначала выяснить +18,981.39 (начальный разрыв, недостающие акты, спорные суммы) | I22: 39 | J22: 0 | K22: =C22+D22+E22 | L22: =ROUND(K22-F22-G22-(0.000000000),2)
A23: ОсОО Ала-Тоо Эйр | B23: -1194328.2 | C23: -1271085.9 | D23: -205594.19 | E23: 282283.89 | F23: -1194396.2 | G23: -1.4551915e-11 | H23: Сдвинуть баланс ETM на -205,594.19 (бот не перенёс продажу: 1; повторная оплата: 1); Исправить 1С на +282,283.89; Сначала выяснить -1,194,396.23 (начальный разрыв, недостающие акты, спорные суммы) | I23: 8 | J23: 0 | K23: =C23+D23+E23 | L23: =ROUND(K23-F23-G23-(-0.000000000),2)
A24: КУТ ЭЙР | B24: 350463.58 | C24: -973150.62 | D24: 1268900 | E24: 58617.52 | F24: 354366.9 | G24: 2.5465852e-11 | H24: Сдвинуть баланс ETM на +1,268,900.00 (оплата не зачислена: 6); Исправить 1С на +58,617.52 (не выставлено в 1С: 2); Сначала выяснить +354,366.90 (начальный разрыв, недостающие акты, спорные суммы) | I24: 13 | J24: 0 | K24: =C24+D24+E24 | L24: =ROUND(K24-F24-G24-(-0.000000000),2)
A25: ТАЛАС ЛАЙН | B25: 0 | C25: -1552513.3 | D25: 1385355.4 | E25: 122057.66 | F25: -45100.25 | G25: 2.1827873e-11 | H25: Сдвинуть баланс ETM на +1,385,355.42 (дубль списания: 2; оплата не зачислена: 4); Исправить 1С на +122,057.66 (не выставлено в 1С: 3); Сначала выяснить -45,100.25 (начальный разрыв, недостающие акты, спорные суммы) | I25: 19 | J25: 0 | K25: =C25+D25+E25 | L25: =ROUND(K25-F25-G25-(0.000000000),2)
A26: Kumtor Tours | B26: 0 | C26: -1370580.2 | D26: 1370323.8 | E26: -5.8207661e-11 | F26: -256.42 | G26: -1.0913936e-11 | H26: Сдвинуть баланс ETM на +1,370,323.80 (дубль списания: 1; оплата не зачислена: 3); Сначала выяснить -256.42 (начальный разрыв, недостающие акты, спорные суммы) | I26: 9 | J26: 0 | K26: =C26+D26+E26 | L26: =ROUND(K26-F26-G26-(-0.000000000),2)
A27: Абдылда уулу Б. | B27: 0 | C27: -1349195.8 | D27: 1073315.9 | E27: 274924.88 | F27: -955.03 | G27: -4.0017767e-11 | H27: Сдвинуть баланс ETM на +1,073,315.90 (бот не перенёс продажу: 5; повторная оплата: 1; оплата не зачислена: 5); Исправить 1С на +274,924.88 (не выставлено в 1С: 6); Сначала выяснить -955.03 (начальный разрыв, недостающие акты, спорные суммы) | I27: 52 | J27: 0 | K27: =C27+D27+E27 | L27: =ROUND(K27-F27-G27-(-0.000000000),2)
A28: Aylana Tour | B28: -155441.16 | C28: -1295071.4 | D28: 863828.28 | E28: 276225.12 | F28: -155017.99 | G28: -7.2759576e-12 | H28: Сдвинуть баланс ETM на +863,828.28 (бот не перенёс продажу: 1; оплата не зачислена: 3); Исправить 1С на +276,225.12 (не выставлено в 1С: 5); Сначала выяснить -155,017.99 (начальный разрыв, недостающие акты, спорные суммы) | I28: 15 | J28: 0 | K28: =C28+D28+E28 | L28: =ROUND(K28-F28-G28-(-0.000000000),2)
A29: Джолдош уулу Эмир | B29: 0 | C29: -1000296.3 | D29: 1107083.8 | E29: -106557.1 | F29: 230.36 | G29: -1.4551915e-11 | H29: Сдвинуть баланс ETM на +1,107,083.81 (оплата не зачислена: 5); Исправить 1С на -106,557.10; Сначала выяснить +230.36 (начальный разрыв, недостающие акты, спорные суммы) | I29: 12 | J29: 0 | K29: =C29+D29+E29 | L29: =ROUND(K29-F29-G29-(-0.000000001),2)
A30: Байтур Трип | B30: 0 | C30: -1135319.5 | D30: 863445.63 | E30: 182592.31 | F30: -89281.6 | G30: 2.910383e-11 | H30: Сдвинуть баланс ETM на +863,445.63 (бот не перенёс продажу: 1; оплата не зачислена: 2); Исправить 1С на +182,592.31 (не выставлено в 1С: 5); Сначала выяснить -89,281.60 (начальный разрыв, недостающие акты, спорные суммы) | I30: 19 | J30: 0 | K30: =C30+D30+E30 | L30: =ROUND(K30-F30-G30-(0.000000000),2)
A31: Бейшенова Н. Ч. | B31: 0 | C31: -1023080.7 | D31: 1076205.7 | E31: -53538.75 | F31: -413.71 | G31: -2.910383e-11 | H31: Сдвинуть баланс ETM на +1,076,205.71 (бот не перенёс продажу: 1; оплата не зачислена: 4); Исправить 1С на -53,538.75 (не выставлено в 1С: 2); Сначала выяснить -413.71 (начальный разрыв, недостающие акты, спорные суммы) | I31: 11 | J31: 0 | K31: =C31+D31+E31 | L31: =ROUND(K31-F31-G31-(0.000000000),2)
A32: Sunrise Tours | B32: 78399.4 | C32: -965356.77 | D32: 1023642.2 | E32: 20437 | F32: 78722.38 | G32: 7.2759576e-12 | H32: Сдвинуть баланс ETM на +1,023,642.15 (дубль списания: 2; оплата не зачислена: 3); Исправить 1С на +20,437.00; Сначала выяснить +78,722.38 (начальный разрыв, недостающие акты, спорные суммы) | I32: 14 | J32: 0 | K32: =C32+D32+E32 | L32: =ROUND(K32-F32-G32-(0.000000000),2)
A33: Жолчу кызы А. | B33: 0 | C33: -1054427.7 | D33: 823200 | E33: 109666.05 | F33: -121561.69 | G33: 0 | H33: Сдвинуть баланс ETM на +823,200.00 (оплата не зачислена: 3); Исправить 1С на +109,666.05 (не выставлено в 1С: 2); Сначала выяснить -121,561.69 (начальный разрыв, недостающие акты, спорные суммы) | I33: 39 | J33: 1 | K33: =C33+D33+E33 | L33: =ROUND(K33-F33-G33-(0.000000000),2)
A34: ОсОО Алтын Эйр | B34: 0 | C34: -1047879.5 | D34: 977000 | E34: 68541.66 | F34: -2337.83 | G34: 2.910383e-11 | H34: Сдвинуть баланс ETM на +977,000.00 (оплата не зачислена: 3); Исправить 1С на +68,541.66 (не выставлено в 1С: 2); Сначала выяснить -2,337.83 (начальный разрыв, недостающие акты, спорные суммы) | I34: 16 | J34: 0 | K34: =C34+D34+E34 | L34: =ROUND(K34-F34-G34-(0.000000001),2)
A35: Жибек Эйр | B35: 253712.49 | C35: -539022.64 | D35: 730395.41 | E35: 18942.32 | F35: 210315.09 | G35: 1.8189894e-11 | H35: Сдвинуть баланс ETM на +730,395.41 (бот не перенёс продажу: 1; повторная оплата: 1; оплата не зачислена: 4); Исправить 1С на +18,942.32; Сначала выяснить +210,315.09 (начальный разрыв, недостающие акты, спорные суммы) | I35: 137 | J35: 2 | K35: =C35+D35+E35 | L35: =ROUND(K35-F35-G35-(0.000000000),2)
A36: Ак-Куу Тур | B36: 0 | C36: -924681.85 | D36: 377308.2 | E36: 542077.42 | F36: -5296.23 | G36: -4.0017767e-11 | H36: Сдвинуть баланс ETM на +377,308.20 (оплата не зачислена: 1); Исправить 1С на +542,077.42 (не выставлено в 1С: 5); Сначала выяснить -5,296.23 (начальный разрыв, недостающие акты, спорные суммы) | I36: 24 | J36: 0 | K36: =C36+D36+E36 | L36: =ROUND(K36-F36-G36-(0.000000000),2)
A37: Абдыраманова Д. А. | B37: 0 | C37: -921359.2 | D37: 815618.71 | E37: 93239.82 | F37: -12500.67 | G37: 2.910383e-11 | H37: Сдвинуть баланс ETM на +815,618.71 (бот не перенёс продажу: 1; оплата не зачислена: 2); Исправить 1С на +93,239.82 (не выставлено в 1С: 1); Сначала выяснить -12,500.67 (начальный разрыв, недостающие акты, спорные суммы) | I37: 9 | J37: 0 | K37: =C37+D37+E37 | L37: =ROUND(K37-F37-G37-(0.000000000),2)
A38: Манас Тур | B38: 195994.52 | C38: -507459.86 | D38: 606654.7 | E38: 96582.32 | F38: 195777.16 | G38: -7.2759576e-12 | H38: Сдвинуть баланс ETM на +606,654.70 (оплата не зачислена: 3); Исправить 1С на +96,582.32 (не выставлено в 1С: 4); Сначала выяснить +195,777.16 (начальный разрыв, недостающие акты, спорные суммы) | I38: 13 | J38: 0 | K38: =C38+D38+E38 | L38: =ROUND(K38-F38-G38-(0.000000000),2)
A39: Bishkek Fly | B39: -265149.11 | C39: -883308.38 | D39: 591694.7 | E39: 26502 | F39: -265111.68 | G39: 0 | H39: Сдвинуть баланс ETM на +591,694.70 (оплата не зачислена: 2); Исправить 1С на +26,502.00 (не выставлено в 1С: 1); Сначала выяснить -265,111.68 (начальный разрыв, недостающие акты, спорные суммы) | I39: 7 | J39: 0 | K39: =C39+D39+E39 | L39: =ROUND(K39-F39-G39-(0.000000000),2)
A40: Issyk-Kul Air | B40: 1.1641532e-10 | C40: -807992.72 | D40: 698600 | E40: 109449.63 | F40: 60.06 | G40: -3.15 | H40: Сдвинуть баланс ETM на +698,600.00 (оплата не зачислена: 1); Исправить 1С на +109,449.63 (не выставлено в 1С: 3); Сначала выяснить +60.06 (начальный разрыв, недостающие акты, спорные суммы) | I40: 8 | J40: 0 | K40: =C40+D40+E40 | L40: =ROUND(K40-F40-G40-(0.000000000),2)
A41: Эсенбеков Кубат Элдияревич | B41: 0 | C41: -750334.62 | D41: 679765.4 | E41: 68944 | F41: -1625.22 | G41: 2.910383e-11 | H41: Сдвинуть баланс ETM на +679,765.40 (бот не перенёс продажу: 1; оплата не зачислена: 4); Исправить 1С на +68,944.00 (не выставлено в 1С: 3); Сначала выяснить -1,625.22 (начальный разрыв, недостающие акты, спорные суммы) | I41: 15 | J41: 0 | K41: =C41+D41+E41 | L41: =ROUND(K41-F41-G41-(-0.000000000),2)
A42: ИП Абдылдаова У. О. | B42: 0 | C42: -729398.09 | D42: 725086.07 | E42: -2.3283064e-10 | F42: -4312.02 | G42: 7.2759576e-12 | H42: Сдвинуть баланс ETM на +725,086.07 (оплата не зачислена: 2); Сначала выяснить -4,312.02 (начальный разрыв, недостающие акты, спорные суммы) | I42: 9 | J42: 0 | K42: =C42+D42+E42 | L42: =ROUND(K42-F42-G42-(-0.000000000),2)
A43: Жибек Авиакасса | B43: 0 | C43: -695485.76 | D43: 690520.07 | E43: 4966.53 | F43: -1.41 | G43: 2.25 | H43: Сдвинуть баланс ETM на +690,520.07 (дубль списания: 2; бот не перенёс продажу: 2; оплата не зачислена: 4); Исправить 1С на +4,966.53 (не выставлено в 1С: 2); Сначала выяснить -1.41 (начальный разрыв, недостающие акты, спорные суммы) | I43: 22 | J43: 0 | K43: =C43+D43+E43 | L43: =ROUND(K43-F43-G43-(0.000000000),2)
A44: Ала-Арча Авиакасса | B44: 0 | C44: -690732.54 | D44: 679892.54 | E44: 10840 | F44: 0 | G44: -1.4551915e-11 | H44: Сдвинуть баланс ETM на +679,892.54 (бот не перенёс продажу: 1; оплата не зачислена: 2); Исправить 1С на +10,840.00 (не выставлено в 1С: 1) | I44: 7 | J44: 0 | K44: =C44+D44+E44 | L44: =ROUND(K44-F44-G44-(-0.000000000),2)
A45: Tengri Trip | B45: 0 | C45: -675730.14 | D45: 571413.94 | E45: 107233.84 | F45: 2915.24 | G45: 2.4 | H45: Сдвинуть баланс ETM на +571,413.94 (бот не перенёс продажу: 1; оплата не зачислена: 2); Исправить 1С на +107,233.84 (не выставлено в 1С: 3); Сначала выяснить +2,915.24 (начальный разрыв, недостающие акты, спорные суммы) | I45: 9 | J45: 0 | K45: =C45+D45+E45 | L45: =ROUND(K45-F45-G45-(0.000000000),2)
A46: ОсОО Чолпон Авиакасса | B46: 0 | C46: -652894.2 | D46: 572154 | E46: 61363.34 | F46: -19376.86 | G46: 1.8189894e-11 | H46: Сдвинуть баланс ETM на +572,154.00 (дубль списания: 1; оплата не зачислена: 2); Исправить 1С на +61,363.34 (не выставлено в 1С: 2); Сначала выяснить -19,376.86 (начальный разрыв, недостающие акты, спорные суммы) | I46: 16 | J46: 0 | K46: =C46+D46+E46 | L46: =ROUND(K46-F46-G46-(0.000000000),2)
A47: ЧОЛПОН ЭЙР | B47: -52420.08 | C47: -643699.56 | D47: 227155.04 | E47: 335485.71 | F47: -81058.81 | G47: -7.2759576e-12 | H47: Сдвинуть баланс ETM на +227,155.04 (дубль списания: 1; повторная оплата: 1; оплата не зачислена: 2); Исправить 1С на +335,485.71 (не выставлено в 1С: 2); Сначала выяснить -81,058.81 (начальный разрыв, недостающие акты, спорные суммы) | I47: 18 | J47: 0 | K47: =C47+D47+E47 | L47: =ROUND(K47-F47-G47-(-0.000000000),2)
A48: ТЯНЬ-ШАНЬ ЭКСПРЕСС | B48: 0 | C48: -634394.83 | D48: 312755.87 | E48: 321614.7 | F48: -24.26 | G48: 5.8207661e-11 | H48: Сдвинуть баланс ETM на +312,755.87 (дубль списания: 1; бот не перенёс продажу: 3; оплата не зачислена: 1); Исправить 1С на +321,614.70 (не выставлено в 1С: 3); Сначала выяснить -24.26 (начальный разрыв, недостающие акты, спорные суммы) | I48: 13 | J48: 0 | K48: =C48+D48+E48 | L48: =ROUND(K48-F48-G48-(-0.000000001),2)
A49: ОсОО Иссык Тур | B49: -149434.14 | C49: -605052.85 | D49: 426756.86 | E49: 26366.4 | F49: -151926.19 | G49: -3.4 | H49: Сдвинуть баланс ETM на +426,756.86 (дубль списания: 1; бот не перенёс продажу: 1; повторная оплата: 2; оплата не зачислена: 3); Исправить 1С на +26,366.40 (не выставлено в 1С: 1); Сначала выяснить -151,926.19 (начальный разрыв, недостающие акты, спорные суммы) | I49: 13 | J49: 0 | K49: =C49+D49+E49 | L49: =ROUND(K49-F49-G49-(-0.000000000),2)
A50: ИП Муратов Э. У. | B50: 0 | C50: -498809.37 | D50: 501968.16 | E50: 45481.96 | F50: 48640.75 | G50: 7.2759576e-12 | H50: Сдвинуть баланс ETM на +501,968.16 (бот не перенёс продажу: 1; оплата не зачислена: 2); Исправить 1С на +45,481.96; Сначала выяснить +48,640.75 (начальный разрыв, недостающие акты, спорные суммы) | I50: 33 | J50: 1 | K50: =C50+D50+E50 | L50: =ROUND(K50-F50-G50-(0.000000000),2)
A51: Урматов Эрлан Сагынович | B51: -8157.11 | C51: -574937.84 | D51: 531376.3 | E51: 34627.28 | F51: -8934.26 | G51: -2.1827873e-11 | H51: Сдвинуть баланс ETM на +531,376.30 (дубль списания: 1; оплата не зачислена: 1; оплата не тому субагенту: 1); Исправить 1С на +34,627.28 (не выставлено в 1С: 1); Сначала выяснить -8,934.26 (начальный разрыв, недостающие акты, спорные суммы) | I51: 10 | J51: 0 | K51: =C51+D51+E51 | L51: =ROUND(K51-F51-G51-(0.000000000),2)
A52: Салам Авиакасса | B52: 0 | C52: -102982.76 | D52: 334078.1 | E52: -231156.28 | F52: -60.94 | G52: -2.910383e-11 | H52: Сдвинуть баланс ETM на +334,078.10 (дубль списания: 1; повторная оплата: 1; оплата не зачислена: 2); Исправить 1С на -231,156.28 (не выставлено в 1С: 1; оплата не проведена: 1); Сначала выяснить -60.94 (начальный разрыв, недостающие акты, спорные суммы) | I52: 14 | J52: 0 | K52: =C52+D52+E52 | L52: =ROUND(K52-F52-G52-(0.000000000),2)
A53: Ak-Bulak Voyage | B53: 0 | C53: 561508.28 | D53: -562800 | E53: -1.4551915e-10 | F53: -1291.72 | G53: 0 | H53: Сдвинуть баланс ETM на -562,800.00 (повторная оплата: 1); Сначала выяснить -1,291.72 (начальный разрыв, недостающие акты, спорные суммы) | I53: 12 | J53: 1 | K53: =C53+D53+E53 | L53: =ROUND(K53-F53-G53-(0.000000000),2)
A54: ИП Жумабекова Б. Н. | B54: -2.910383e-11 | C54: -21070.95 | D54: 283613.75 | E54: -262542.8 | F54: -1.1641532e-10 | G54: 0 | H54: Сдвинуть баланс ETM на +283,613.75 (бот не перенёс продажу: 2; оплата не зачислена: 1); Исправить 1С на -262,542.80 (не выставлено в 1С: 1) | I54: 32 | J54: 1 | K54: =C54+D54+E54 | L54: =ROUND(K54-F54-G54-(-0.000000000),2)
A55: Осмонова А. Н. | B55: 0 | C55: -541422.25 | D55: 493300 | E55: 48122.25 | F55: 0 | G55: -1.4551915e-11 | H55: Сдвинуть баланс ETM на +493,300.00 (оплата не зачислена: 1); Исправить 1С на +48,122.25 (не выставлено в 1С: 3) | I55: 7 | J55: 0 | K55: =C55+D55+E55 | L55: =ROUND(K55-F55-G55-(0.000000000),2)
A56: ИП Джолдошов Д. У. | B56: 0 | C56: -533236.5 | D56: 533140.14 | E56: 0 | F56: -96.36 | G56: 0 | H56: Сдвинуть баланс ETM на +533,140.14 (оплата не зачислена: 3); Сначала выяснить -96.36 (начальный разрыв, недостающие акты, спорные суммы) | I56: 9 | J56: 0 | K56: =C56+D56+E56 | L56: =ROUND(K56-F56-G56-(-0.000000000),2)
A57: Урматова Айпери Нурбековна | B57: 0 | C57: -525719.1 | D57: 418752.76 | E57: 106984 | F57: 17.66 | G57: 3.6379788e-12 | H57: Сдвинуть баланс ETM на +418,752.76 (бот не перенёс продажу: 1; оплата не зачислена: 1); Исправить 1С на +106,984.00 (не выставлено в 1С: 1); Сначала выяснить +17.66 (начальный разрыв, недостающие акты, спорные суммы) | I57: 12 | J57: 0 | K57: =C57+D57+E57 | L57: =ROUND(K57-F57-G57-(0.000000000),2)
A58: ЫЙЫК ЭКСПРЕСС | B58: -386181.95 | C58: -456398.18 | D58: -27243.22 | E58: 97636.01 | F58: -386005.39 | G58: 2.5465852e-11 | H58: Сдвинуть баланс ETM на -27,243.22 (бот не перенёс продажу: 1; повторная оплата: 1; оплата не зачислена: 2); Исправить 1С на +97,636.01 (не выставлено в 1С: 4); Сначала выяснить -386,005.39 (начальный разрыв, недостающие акты, спорные суммы) | I58: 20 | J58: 0 | K58: =C58+D58+E58 | L58: =ROUND(K58-F58-G58-(0.000000000),2)
A59: ИП Турсунов Т. А. | B59: 0 | C59: -499892.76 | D59: 504179.62 | E59: -4286.86 | F59: 0 | G59: 2.5465852e-11 | H59: Сдвинуть баланс ETM на +504,179.62 (оплата не зачислена: 2); Исправить 1С на -4,286.86 | I59: 6 | J59: 0 | K59: =C59+D59+E59 | L59: =ROUND(K59-F59-G59-(-0.000000000),2)
A60: БАЙТУР ТУРИЗМ | B60: 0 | C60: -497630.87 | D60: 309501.73 | E60: 188129.14 | F60: 0 | G60: -1.4551915e-11 | H60: Сдвинуть баланс ETM на +309,501.73 (оплата не зачислена: 1); Исправить 1С на +188,129.14 (не выставлено в 1С: 1) | I60: 5 | J60: 0 | K60: =C60+D60+E60 | L60: =ROUND(K60-F60-G60-(0.000000000),2)
A61: ОсОО Кок-Жайык Лайн | B61: 0 | C61: -472618.62 | D61: 436735.12 | E61: 46205.62 | F61: 10322.12 | G61: -1.8189894e-11 | H61: Сдвинуть баланс ETM на +436,735.12 (дубль списания: 1; оплата не зачислена: 1); Исправить 1С на +46,205.62 (не выставлено в 1С: 1); Сначала выяснить +10,322.12 (начальный разрыв, недостающие акты, спорные суммы) | I61: 13 | J61: 0 | K61: =C61+D61+E61 | L61: =ROUND(K61-F61-G61-(0.000000000),2)
A62: ОсОО Ала-Арча Трип | B62: 0 | C62: 119617.25 | D62: 166200 | E62: -285788.02 | F62: 29.23 | G62: 1.4551915e-11 | H62: Сдвинуть баланс ETM на +166,200.00 (оплата не зачислена: 1); Исправить 1С на -285,788.02; Сначала выяснить +29.23 (начальный разрыв, недостающие акты, спорные суммы) | I62: 5 | J62: 0 | K62: =C62+D62+E62 | L62: =ROUND(K62-F62-G62-(-0.000000000),2)
A63: Эсенбекова Айгуль Нурбекевна | B63: 0 | C63: -448734.06 | D63: 408092.2 | E63: 40641.86 | F63: 0 | G63: 0 | H63: Сдвинуть баланс ETM на +408,092.20 (оплата не зачислена: 1); Исправить 1С на +40,641.86 (не выставлено в 1С: 1) | I63: 6 | J63: 0 | K63: =C63+D63+E63 | L63: =ROUND(K63-F63-G63-(0.000000000),2)
A64: Ниязбеков Кубат Таалайевич | B64: -411896.58 | C64: -429168.52 | D64: 0 | E64: 17285.11 | F64: -411883.41 | G64: 0 | H64: Исправить 1С на +17,285.11 (не выставлено в 1С: 1); Сначала выяснить -411,883.41 (начальный разрыв, недостающие акты, спорные суммы) | I64: 3 | J64: 0 | K64: =C64+D64+E64 | L64: =ROUND(K64-F64-G64-(-0.000000000),2)
A65: Чынар уулу Эмир | B65: 5.8207661e-11 | C65: -395784.04 | D65: -8392.82 | E65: 68199.89 | F65: -335976.97 | G65: 0 | H65: Сдвинуть баланс ETM на -8,392.82 (дубль списания: 1; бот не перенёс продажу: 1); Исправить 1С на +68,199.89 (не выставлено в 1С: 1); Сначала выяснить -335,976.97 (начальный разрыв, недостающие акты, спорные суммы) | I65: 22 | J65: 2 | K65: =C65+D65+E65 | L65: =ROUND(K65-F65-G65-(0.000000000),2)
A66: Асанов Кубат Чынаревич | B66: 0 | C66: -403058.92 | D66: 288100 | E66: 115067.94 | F66: 109.02 | G66: 1.4551915e-11 | H66: Сдвинуть баланс ETM на +288,100.00 (оплата не зачислена: 1); Исправить 1С на +115,067.94 (не выставлено в 1С: 1); Сначала выяснить +109.02 (начальный разрыв, недостающие акты, спорные суммы) | I66: 5 | J66: 1 | K66: =C66+D66+E66 | L66: =ROUND(K66-F66-G66-(0.000000000),2)
A67: ОсОО Кара-Кол Трип | B67: 278432.52 | C67: 160339.06 | D67: -557.32 | E67: 121261.28 | F67: 281043.02 | G67: 7.2759576e-12 | H67: Сдвинуть баланс ETM на -557.32; Исправить 1С на +121,261.28 (не выставлено в 1С: 3); Сначала выяснить +281,043.02 (начальный разрыв, недостающие акты, спорные суммы) | I67: 10 | J67: 0 | K67: =C67+D67+E67 | L67: =ROUND(K67-F67-G67-(0.000000000),2)
A68: Ыйык Авиакасса | B68: 0 | C68: -252719.8 | D68: 325175.92 | E68: -72490 | F68: -33.88 | G68: 0 | H68: Сдвинуть баланс ETM на +325,175.92 (бот не перенёс продажу: 1; повторная оплата: 1; оплата не зачислена: 3); Исправить 1С на -72,490.00; Сначала выяснить -33.88 (начальный разрыв, недостающие акты, спорные суммы) | I68: 8 | J68: 0 | K68: =C68+D68+E68 | L68: =ROUND(K68-F68-G68-(-0.000000000),2)
A69: ИП Бейшенова Д. О. | B69: 0 | C69: -377401.48 | D69: 182955 | E69: 194587.71 | F69: 141.23 | G69: 1.4551915e-11 | H69: Сдвинуть баланс ETM на +182,955.00 (бот не перенёс продажу: 1; повторная оплата: 1; оплата не зачислена: 2); Исправить 1С на +194,587.71 (не выставлено в 1С: 7); Сначала выяснить +141.23 (начальный разрыв, недостающие акты, спорные суммы) | I69: 19 | J69: 0 | K69: =C69+D69+E69 | L69: =ROUND(K69-F69-G69-(0.000000000),2)
A70: Бирлик Трип | B70: 0 | C70: -373396.09 | D70: 346306.04 | E70: 26997.4 | F70: -92.65 | G70: 7.2759576e-12 | H70: Сдвинуть баланс ETM на +346,306.04 (бот не перенёс продажу: 1; повторная оплата: 1; оплата не зачислена: 2); Исправить 1С на +26,997.40; Сначала выяснить -92.65 (начальный разрыв, недостающие акты, спорные суммы) | I70: 11 | J70: 0 | K70: =C70+D70+E70 | L70: =ROUND(K70-F70-G70-(0.000000000),2)
A71: Чолпон Тревел | B71: 0 | C71: -260225.1 | D71: 260400 | E71: 55058.69 | F71: 55233.59 | G71: 0 | H71: Сдвинуть баланс ETM на +260,400.00 (оплата не зачислена: 1); Исправить 1С на +55,058.69; Сначала выяснить +55,233.59 (начальный разрыв, недостающие акты, спорные суммы) | I71: 21 | J71: 2 | K71: =C71+D71+E71 | L71: =ROUND(K71-F71-G71-(-0.000000000),2)
A72: ТАЛАС ВОЯЖ | B72: -318941 | C72: -291809.84 | D72: 11168.84 | E72: -38300 | F72: -318941 | G72: 0 | H72: Сдвинуть баланс ETM на +11,168.84; Исправить 1С на -38,300.00; Сначала выяснить -318,941.00 (начальный разрыв, недостающие акты, спорные суммы) | I72: 7 | J72: 0 | K72: =C72+D72+E72 | L72: =ROUND(K72-F72-G72-(0.000000000),2)
A73: САЛАМ ВОЯЖ | B73: 0 | C73: 141941.69 | D73: 98612 | E73: -240553.69 | F73: 0 | G73: 7.2759576e-12 | H73: Сдвинуть баланс ETM на +98,612.00 (оплата не зачислена: 1); Исправить 1С на -240,553.69 (не выставлено в 1С: 1) | I73: 4 | J73: 0 | K73: =C73+D73+E73 | L73: =ROUND(K73-F73-G73-(0.000000000),2)
A74: Асанова Каныкей Эсенбекевна | B74: -320853.24 | C74: -327069.44 | D74: 11347.2 | E74: -5131 | F74: -320853.24 | G74: -1.4551915e-11 | H74: Сдвинуть баланс ETM на +11,347.20 (дубль списания: 1; бот не перенёс продажу: 1); Исправить 1С на -5,131.00; Сначала выяснить -320,853.24 (начальный разрыв, недостающие акты, спорные суммы) | I74: 5 | J74: 0 | K74: =C74+D74+E74 | L74: =ROUND(K74-F74-G74-(0.000000000),2)
A75: ИП Асанов К. Б. | B75: 0 | C75: -329894.34 | D75: 201202.39 | E75: 125841.06 | F75: -2850.89 | G75: -3.6379788e-12 | H75: Сдвинуть баланс ETM на +201,202.39 (оплата не зачислена: 1); Исправить 1С на +125,841.06 (не выставлено в 1С: 2); Сначала выяснить -2,850.89 (начальный разрыв, недостающие акты, спорные суммы) | I75: 21 | J75: 1 | K75: =C75+D75+E75 | L75: =ROUND(K75-F75-G75-(-0.000000000),2)
A76: Кенешова Чолпон Таалайовна | B76: 0 | C76: -329379.63 | D76: 122328.62 | E76: 206693.3 | F76: -357.71 | G76: 1.8189894e-11 | H76: Сдвинуть баланс ETM на +122,328.62 (бот не перенёс продажу: 1; оплата не зачислена: 1); Исправить 1С на +206,693.30 (не выставлено в 1С: 4); Сначала выяснить -357.71 (начальный разрыв, недостающие акты, спорные суммы) | I76: 10 | J76: 0 | K76: =C76+D76+E76 | L76: =ROUND(K76-F76-G76-(0.000000000),2)
A77: САЛАМ ЭЙР | B77: -1.1641532e-10 | C77: -326737.55 | D77: 8333.7 | E77: 314382.85 | F77: -4021 | G77: 7.2759576e-12 | H77: Сдвинуть баланс ETM на +8,333.70 (дубль списания: 1); Исправить 1С на +314,382.85 (не выставлено в 1С: 7); Сначала выяснить -4,021.00 (начальный разрыв, недостающие акты, спорные суммы) | I77: 15 | J77: 0 | K77: =C77+D77+E77 | L77: =ROUND(K77-F77-G77-(0.000000000),2)
A78: Абдылдаов Д. М. | B78: 0 | C78: -300901.93 | D78: 290833.38 | E78: 10000 | F78: -68.55 | G78: 1.8189894e-11 | H78: Сдвинуть баланс ETM на +290,833.38 (оплата не зачислена: 2); Исправить 1С на +10,000.00; Сначала выяснить -68.55 (начальный разрыв, недостающие акты, спорные суммы) | I78: 11 | J78: 0 | K78: =C78+D78+E78 | L78: =ROUND(K78-F78-G78-(-0.000000000),2)
A79: Тянь-Шань Тур | B79: 0 | C79: 259874.08 | D79: -279600 | E79: 11971.97 | F79: -7753.95 | G79: -3.6379788e-12 | H79: Сдвинуть баланс ETM на -279,600.00 (повторная оплата: 1); Исправить 1С на +11,971.97; Сначала выяснить -7,753.95 (начальный разрыв, недостающие акты, спорные суммы) | I79: 38 | J79: 2 | K79: =C79+D79+E79 | L79: =ROUND(K79-F79-G79-(0.000000000),2)
A80: Манас Туризм | B80: 0 | C80: -297776.32 | D80: 234600 | E80: 36000 | F80: -27176.32 | G80: 0 | H80: Сдвинуть баланс ETM на +234,600.00 (оплата не зачислена: 1); Исправить 1С на +36,000.00; Сначала выяснить -27,176.32 (начальный разрыв, недостающие акты, спорные суммы) | I80: 22 | J80: 1 | K80: =C80+D80+E80 | L80: =ROUND(K80-F80-G80-(-0.000000000),2)
A81: СОН-КУЛЬ ТУР | B81: -1.1641532e-10 | C81: -278350.28 | D81: 280731.3 | E81: -2506.47 | F81: -122.85 | G81: -2.6 | H81: Сдвинуть баланс ETM на +280,731.30 (оплата не зачислена: 1); Исправить 1С на -2,506.47; Сначала выяснить -122.85 (начальный разрыв, недостающие акты, спорные суммы) | I81: 6 | J81: 0 | K81: =C81+D81+E81 | L81: =ROUND(K81-F81-G81-(0.000000000),2)
A82: ИП Мамбетова Ч. Э. | B82: 0 | C82: -102521.91 | D82: 179757.21 | E82: -77452.14 | F82: -216.84 | G82: 3.6379788e-12 | H82: Сдвинуть баланс ETM на +179,757.21 (бот не перенёс продажу: 1; оплата не зачислена: 1); Исправить 1С на -77,452.14 (не выставлено в 1С: 1); Сначала выяснить -216.84 (начальный разрыв, недостающие акты, спорные суммы) | I82: 12 | J82: 0 | K82: =C82+D82+E82 | L82: =ROUND(K82-F82-G82-(0.000000000),2)
A83: Чынарова Бурул Джолдошовна | B83: 0 | C83: -251755.08 | D83: 223698 | E83: 28040.51 | F83: -16.57 | G83: 7.2759576e-12 | H83: Сдвинуть баланс ETM на +223,698.00 (бот не перенёс продажу: 1; оплата не зачислена: 2); Исправить 1С на +28,040.51 (не выставлено в 1С: 2); Сначала выяснить -16.57 (начальный разрыв, недостающие акты, спорные суммы) | I83: 16 | J83: 0 | K83: =C83+D83+E83 | L83: =ROUND(K83-F83-G83-(0.000000000),2)
A84: ОсОО Кок-Жайык Вояж | B84: 0 | C84: -250963.79 | D84: 156975.33 | E84: 94176.83 | F84: 192.32 | G84: -3.95 | H84: Сдвинуть баланс ETM на +156,975.33 (бот не перенёс продажу: 2; оплата не зачислена: 1); Исправить 1С на +94,176.83 (не выставлено в 1С: 2); Сначала выяснить +192.32 (начальный разрыв, недостающие акты, спорные суммы) | I84: 11 | J84: 0 | K84: =C84+D84+E84 | L84: =ROUND(K84-F84-G84-(0.000000000),2)
A85: Silk Route Air | B85: 170347.21 | C85: 97886.44 | D85: 17033.55 | E85: 55877.56 | F85: 170797.55 | G85: -7.2759576e-12 | H85: Сдвинуть баланс ETM на +17,033.55 (дубль списания: 1); Исправить 1С на +55,877.56 (не выставлено в 1С: 1); Сначала выяснить +170,797.55 (начальный разрыв, недостающие акты, спорные суммы) | I85: 9 | J85: 0 | K85: =C85+D85+E85 | L85: =ROUND(K85-F85-G85-(0.000000000),2)
A86: Эсенбек уулу Азамат | B86: 0 | C86: -236889.98 | D86: 169500 | E86: 24228.98 | F86: -43161 | G86: 0 | H86: Сдвинуть баланс ETM на +169,500.00 (оплата не зачислена: 1); Исправить 1С на +24,228.98 (не выставлено в 1С: 1); Сначала выяснить -43,161.00 (начальный разрыв, недостающие акты, спорные суммы) | I86: 4 | J86: 0 | K86: =C86+D86+E86 | L86: =ROUND(K86-F86-G86-(0.000000000),2)
A87: Blue Bird Travel | B87: -1.0913936e-11 | C87: -234553.82 | D87: 40052.1 | E87: 190265.88 | F87: -4235.84 | G87: -1.4551915e-11 | H87: Сдвинуть баланс ETM на +40,052.10 (повторная оплата: 1; оплата не зачислена: 1); Исправить 1С на +190,265.88 (не выставлено в 1С: 7); Сначала выяснить -4,235.84 (начальный разрыв, недостающие акты, спорные суммы) | I87: 18 | J87: 0 | K87: =C87+D87+E87 | L87: =ROUND(K87-F87-G87-(0.000000000),2)
A88: ТАЛАС ЭЙР | B88: 0 | C88: 96990.57 | D88: -160486.75 | E88: 63496.18 | F88: 0 | G88: -1.4551915e-11 | H88: Сдвинуть баланс ETM на -160,486.75 (дубль списания: 1; повторная оплата: 1); Исправить 1С на +63,496.18 (не выставлено в 1С: 2) | I88: 4 | J88: 0 | K88: =C88+D88+E88 | L88: =ROUND(K88-F88-G88-(-0.000000000),2)
A89: Жибек Вояж | B89: 0 | C89: -181710.95 | D89: 181812.57 | E89: -14620 | F89: -14518.38 | G89: 3.6379788e-12 | H89: Сдвинуть баланс ETM на +181,812.57 (бот не перенёс продажу: 1; оплата не зачислена: 1); Исправить 1С на -14,620.00; Сначала выяснить -14,518.38 (начальный разрыв, недостающие акты, спорные суммы) | I89: 18 | J89: 1 | K89: =C89+D89+E89 | L89: =ROUND(K89-F89-G89-(-0.000000000),2)
A90: Жумабек кызы Умут | B90: -85204.1 | C90: -167809.18 | D90: -11438 | E90: 93750 | F90: -85500.18 | G90: 3 | H90: Сдвинуть баланс ETM на -11,438.00 (дубль списания: 1; бот не перенёс продажу: 1); Исправить 1С на +93,750.00; Сначала выяснить -85,500.18 (начальный разрыв, недостающие акты, спорные суммы) | I90: 8 | J90: 0 | K90: =C90+D90+E90 | L90: =ROUND(K90-F90-G90-(0.000000000),2)
A91: Манас Вояж | B91: 0 | C91: -148790.7 | D91: -8178.21 | E91: 161366.43 | F91: 4397.52 | G91: 1.4551915e-11 | H91: Сдвинуть баланс ETM на -8,178.21; Исправить 1С на +161,366.43 (не выставлено в 1С: 3); Сначала выяснить +4,397.52 (начальный разрыв, недостающие акты, спорные суммы) | I91: 11 | J91: 0 | K91: =C91+D91+E91 | L91: =ROUND(K91-F91-G91-(0.000000000),2)
A92: Мамбет уулу Чынгыз | B92: 114616.29 | C92: 72497.74 | D92: 47373.28 | E92: -5155.49 | F92: 114715.53 | G92: 1.4551915e-11 | H92: Сдвинуть баланс ETM на +47,373.28; Исправить 1С на -5,155.49; Сначала выяснить +114,715.53 (начальный разрыв, недостающие акты, спорные суммы) | I92: 7 | J92: 0 | K92: =C92+D92+E92 | L92: =ROUND(K92-F92-G92-(-0.000000000),2)
A93: ИП Элдиярова А. Ч. | B93: 0 | C93: -157391.1 | D93: 158500 | E93: -5.8207661e-11 | F93: 1108.9 | G93: 0 | H93: Сдвинуть баланс ETM на +158,500.00 (оплата не зачислена: 1); Сначала выяснить +1,108.90 (начальный разрыв, недостающие акты, спорные суммы) | I93: 3 | J93: 0 | K93: =C93+D93+E93 | L93: =ROUND(K93-F93-G93-(-0.000000000),2)
A94: Иссык Вояж | B94: -107659.19 | C94: -149923.37 | D94: 270.18 | E94: 41994 | F94: -107659.19 | G94: 7.2759576e-12 | H94: Сдвинуть баланс ETM на +270.18; Исправить 1С на +41,994.00 (не выставлено в 1С: 2); Сначала выяснить -107,659.19 (начальный разрыв, недостающие акты, спорные суммы) | I94: 6 | J94: 0 | K94: =C94+D94+E94 | L94: =ROUND(K94-F94-G94-(-0.000000000),2)
A95: Сыдыков С. У. | B95: 0 | C95: -4563.6 | D95: -68433.4 | E95: 8024.99 | F95: -64972.01 | G95: 0 | H95: Сдвинуть баланс ETM на -68,433.40 (дубль списания: 1; бот не перенёс продажу: 1); Исправить 1С на +8,024.99 (не выставлено в 1С: 2); Сначала выяснить -64,972.01 (начальный разрыв, недостающие акты, спорные суммы) | I95: 22 | J95: 1 | K95: =C95+D95+E95 | L95: =ROUND(K95-F95-G95-(0.000000000),2)
A96: ИП Абдыраманова Ж. Д. | B96: 0 | C96: -57104.62 | D96: -32171.09 | E96: 89108.87 | F96: -166.84 | G96: 0 | H96: Сдвинуть баланс ETM на -32,171.09 (бот не перенёс продажу: 1); Исправить 1С на +89,108.87 (не выставлено в 1С: 5); Сначала выяснить -166.84 (начальный разрыв, недостающие акты, спорные суммы) | I96: 9 | J96: 0 | K96: =C96+D96+E96 | L96: =ROUND(K96-F96-G96-(-0.000000000),2)
A97: Сатарова А. О. | B97: 0 | C97: 115054.94 | D97: -114986.26 | E97: 9.8225428e-11 | F97: 69.48 | G97: -0.8 | H97: Сдвинуть баланс ETM на -114,986.26 (бот не перенёс продажу: 2); Сначала выяснить +69.48 (начальный разрыв, недостающие акты, спорные суммы) | I97: 4 | J97: 0 | K97: =C97+D97+E97 | L97: =ROUND(K97-F97-G97-(0.000000000),2)
A98: Jailoo Trip | B98: 5.8207661e-11 | C98: 58975.46 | D98: -80274.52 | E98: 21400.38 | F98: 101.32 | G98: 1.4551915e-11 | H98: Сдвинуть баланс ETM на -80,274.52 (бот не перенёс продажу: 1); Исправить 1С на +21,400.38 (не выставлено в 1С: 1); Сначала выяснить +101.32 (начальный разрыв, недостающие акты, спорные суммы) | I98: 9 | J98: 0 | K98: =C98+D98+E98 | L98: =ROUND(K98-F98-G98-(0.000000000),2)
A99: Сатарова Жылдыз Жумабековна | B99: 0 | C99: -99722.73 | D99: 0 | E99: 98831 | F99: -891.73 | G99: -3.6379788e-12 | H99: Исправить 1С на +98,831.00 (не выставлено в 1С: 2); Сначала выяснить -891.73 (начальный разрыв, недостающие акты, спорные суммы) | I99: 7 | J99: 0 | K99: =C99+D99+E99 | L99: =ROUND(K99-F99-G99-(0.000000000),2)
A100: Ниязбекова Асель Сатаровна | B100: 0 | C100: -61104.43 | D100: 32254.69 | E100: 34927.94 | F100: 6080.45 | G100: -2.25 | H100: Сдвинуть баланс ETM на +32,254.69 (дубль списания: 1); Исправить 1С на +34,927.94 (не выставлено в 1С: 1); Сначала выяснить +6,080.45 (начальный разрыв, недостающие акты, спорные суммы) | I100: 6 | J100: 0 | K100: =C100+D100+E100 | L100: =ROUND(K100-F100-G100-(-0.000000000),2)
A101: Небо Авиа | B101: -53386.52 | C101: -54046.82 | D101: 0 | E101: 0 | F101: -54046.82 | G101: -2.910383e-11 | H101: Сначала выяснить -54,046.82 (начальный разрыв, недостающие акты, спорные суммы) | I101: 3 | J101: 0 | K101: =C101+D101+E101 | L101: =ROUND(K101-F101-G101-(0.000000000),2)
...

Sheet Мост
A1: Баланс-мост по субагентам (без заплаток): разрыв на конец = начальный разрыв + сумма найденных причин
A2: Каждая строка 1С и ETM попала ровно в одну колонку. «Не объяснено» — формула. Колонки «акт не выгружен» и «скачок через пропуск» — честно нераспределённые суммы, а не ошибки.
A3: Субагент | B3: Разрыв на конец | C3: Разрыв на начало | D3: 1С: разрыв между актами | E3: 1С: скачок через пропущенный акт | F3: 1С: арифметика акта | G3: Округления сошедшихся групп | H3: Сумма: ошибка 1С | I3: Сумма: ошибка бота | J3: Сумма: нужна проверка | K3: Двойное списание | L3: Бот не перенёс продажу | M3: Только 1С, без реестра | N3: Есть в ETM, нет в 1С | O3: Войд не закрыт | P3: ETM: акт не выгружен | Q3: Оплата не проведена в 1С | R3: Оплата не зачислена в ETM | S3: Повторная оплата | T3: Оплата не тому субагенту | U3: Оплата: акт не выгружен | V3: Сумма причин | W3: Не объяснено (формула)
A4: Ak-Bulak Voyage | B4: 561508.28 | C4: 0 | D4: 0 | E4: 501087.88 | F4: 1.4551915e-10 | G4: 0 | H4: 0 | I4: 0 | J4: -97936.08 | K4: 0 | L4: 0 | M4: 0 | N4: 0 | O4: 0 | P4: -404443.52 | Q4: 0 | R4: 0 | S4: 562800 | T4: 0 | U4: 0 | V4: =SUM(C4:U4) | W4: =ROUND(B4-V4,4)
A5: Ala-Too Travel | B5: -3317307.5 | C5: -3233430.5 | D5: 0 | E5: 0 | F5: -1.2369128e-10 | G5: -1.4551915e-11 | H5: 0 | I5: 0 | J5: -17.83 | K5: 0 | L5: 0 | M5: 0 | N5: -83859.22 | O5: 0 | P5: 0 | Q5: 0 | R5: 0 | S5: 0 | T5: 0 | U5: 0 | V5: =SUM(C5:U5) | W5: =ROUND(B5-V5,4)
A6: Aylana Tour | B6: -1295071.4 | C6: -155441.16 | D6: 27500 | E6: 0 | F6: -1.1641532e-10 | G6: -7.2759576e-12 | H6: -69823.61 | I6: -1903.84 | J6: 423.17 | K6: 0 | L6: 43175.56 | M6: 0 | N6: -233901.51 | O6: 0 | P6: 0 | Q6: 0 | R6: -905100 | S6: 0 | T6: 0 | U6: 0 | V6: =SUM(C6:U6) | W6: =ROUND(B6-V6,4)
A7: Bishkek Fly | B7: -883308.38 | C7: -265149.11 | D7: 0 | E7: 0 | F7: 0 | G7: 0 | H7: -13526 | I7: -1094.7 | J7: 37.43 | K7: 0 | L7: 0 | M7: 0 | N7: -12976 | O7: 0 | P7: 0 | Q7: 0 | R7: -590600 | S7: 0 | T7: 0 | U7: 0 | V7: =SUM(C7:U7) | W7: =ROUND(B7-V7,4)
A8: Blue Bird Travel | B8: -234553.82 | C8: -1.0913936e-11 | D8: 0 | E8: 0 | F8: -8.0035534e-11 | G8: -1.4551915e-11 | H8: 7200 | I8: -16352.1 | J8: -4235.84 | K8: 0 | L8: 0 | M8: 0 | N8: -197465.88 | O8: 0 | P8: 0 | Q8: 0 | R8: -149400 | S8: 125700 | T8: 0 | U8: 0 | V8: =SUM(C8:U8) | W8: =ROUND(B8-V8,4)
A9: Issyk-Kul Air | B9: -807992.72 | C9: 1.1641532e-10 | D9: 0 | E9: 0 | F9: 1.1641532e-10 | G9: -3.15 | H9: 8171.37 | I9: 0 | J9: 60.06 | K9: 0 | L9: 0 | M9: 0 | N9: -117621 | O9: 0 | P9: 0 | Q9: 0 | R9: -698600 | S9: 0 | T9: 0 | U9: 0 | V9: =SUM(C9:U9) | W9: =ROUND(B9-V9,4)
A10: Jailoo Trip | B10: 58975.46 | C10: 5.8207661e-11 | D10: 0 | E10: 0 | F10: -1.4551915e-10 | G10: 1.4551915e-11 | H10: -800 | I10: 7189.48 | J10: 101.32 | K10: 0 | L10: 73085.04 | M10: 0 | N10: -20600.38 | O10: 0 | P10: 0 | Q10: 0 | R10: 0 | S10: 0 | T10: 0 | U10: 0 | V10: =SUM(C10:U10) | W10: =ROUND(B10-V10,4)
A11: Karakol Express | B11: -3899769.5 | C11: 23846.3 | D11: 0 | E11: 0 | F11: -3.4924597e-10 | G11: -4.65 | H11: 342534.01 | I11: -8013.7 | J11: 26014.83 | K11: -65928.6 | L11: 270524.17 | M11: 0 | N11: -718741.85 | O11: 0 | P11: 0 | Q11: 0 | R11: -4274600 | S11: 504600 | T11: 0 | U11: 0 | V11: =SUM(C11:U11) | W11: =ROUND(B11-V11,4)
A12: Kumtor Tours | B12: -1370580.2 | C12: 0 | D12: 0 | E12: 0 | F12: 5.8207661e-11 | G12: -1.0913936e-11 | H12: 0 | I12: -27000 | J12: -256.42 | K12: -28223.8 | L12: 0 | M12: 0 | N12: 0 | O12: 0 | P12: 0 | Q12: 0 | R12: -1315100 | S12: 0 | T12: 0 | U12: 0 | V12: =SUM(C12:U12) | W12: =ROUND(B12-V12,4)
A13: Nomad Trip | B13: 24188.38 | C13: 0 | D13: 107557.1 | E13: 0 | F13: -6.5483619e-11 | G13: 1.4551915e-11 | H13: 0 | I13: 424.64 | J13: -123.95 | K13: 0 | L13: 0 | M13: 0 | N13: -83669.41 | O13: 0 | P13: 0 | Q13: 0 | R13: 0 | S13: 0 | T13: 0 | U13: 0 | V13: =SUM(C13:U13) | W13: =ROUND(B13-V13,4)
A14: Silk Route Air | B14: 97886.44 | C14: 170347.21 | D14: 0 | E14: 0 | F14: 0 | G14: -7.2759576e-12 | H14: 1345.55 | I14: 2648.45 | J14: 450.34 | K14: -19682 | L14: 0 | M14: 0 | N14: -57223.11 | O14: 0 | P14: 0 | Q14: 0 | R14: 0 | S14: 0 | T14: 0 | U14: 0 | V14: =SUM(C14:U14) | W14: =ROUND(B14-V14,4)
A15: SkyWay Travel | B15: -8740000 | C15: 0 | D15: 27500 | E15: 0 | F15: 1.9390427e-09 | G15: -4.91 | H15: -224084.64 | I15: -2384.48 | J15: -27327.17 | K15: -128165.95 | L15: 354548.84 | M15: 0 | N15: -1109681.7 | O15: 0 | P15: 0 | Q15: 0 | R15: -8041200 | S15: 410800 | T15: 0 | U15: 0 | V15: =SUM(C15:U15) | W15: =ROUND(B15-V15,4)
... A103: Эсенбекова Айгуль Нурбекевна | B103: -448734.06 | C103: 0 | D103: 0 | E103: 0 | F103: -2.0008883e-11 | G103: 0 | H103: 0 | I103: 407.8 | J103: 0 | K103: 0 | L103: 0 | M103: 0 | N103: -40641.86 | O103: 0 | P103: 0 | Q103: 0 | R103: -408500 | S103: 0 | T103: 0 | U103: 0 | V103: =SUM(C103:U103) | W103: =ROUND(B103-V103,4)
A104: ИТОГО | B104: =SUM(B4:B103) | C104: =SUM(C4:C103) | D104: =SUM(D4:D103) | E104: =SUM(E4:E103) | F104: =SUM(F4:F103) | G104: =SUM(G4:G103) | H104: =SUM(H4:H103) | I104: =SUM(I4:I103) | ... W104: =SUM(W4:W103)

Sheet Мост по месяцам
A1: Помесячная проверка тождества (без подгонки)
A2: Изменение разрыва за месяц обязано равняться: арифметика акта + оборот 1С + оборот ETM. «Остаток тождества» — формула.
A3: Субагент | B3: Месяц | C3: Сальдо 1С начало | D3: Сальдо 1С конец | E3: Оборот 1С | F3: Баланс ETM начало | G3: Баланс ETM конец | H3: Оборот ETM | I3: Разрыв начало | J3: Разрыв конец | K3: Арифметика акта | L3: Разрыв сальдо между актами? | M3: Скачок сальдо 1С на входе | N3: Остаток тождества (≈0)
A4: Ak-Bulak Voyage | B4: 2026-01 | C4: 0 | D4: -398788.25 | E4: -398788.25 | F4: 0 | G4: 398781.33 | H4: 398781.33 | I4: 0 | J4: -6.92 | K4: 0 | L4: FALSE | M4: 0 | N4: =ROUND((J4-I4)-(K4+E4+H4),4)
A5: Ak-Bulak Voyage | B5: 2026-03 | C5: 102299.63 | D5: -162591.5 | E5: -264891.13 | F5: -103591.35 | G5: 724099.78 | H5: 827691.13 | I5: -1291.72 | J5: 561508.28 | K5: 0 | L5: FALSE | M5: 501087.88 | N5: =ROUND((J5-I5)-(K5+E5+H5),4)
A6: Ak-Bulak Voyage | B6: 2026-04 | C6: -162591.5 | D6: -253907.41 | E6: -91315.91 | F6: 724099.78 | G6: 815415.69 | H6: 91315.91 | I6: 561508.28 | J6: 561508.28 | K6: -2.910383e-11 | L6: FALSE | M6: 0 | N6: =ROUND((J6-I6)-(K6+E6+H6),4)
A7: Ak-Bulak Voyage | B7: 2026-05 | C7: -253907.41 | D7: -610056.98 | E7: -356149.57 | F7: 815415.69 | G7: 1171565.3 | H7: 356149.57 | I7: 561508.28 | J7: 561508.28 | K7: 1.1641532e-10 | L7: FALSE | M7: 0 | N7: =ROUND((J7-I7)-(K7+E7+H7),4)
A8: Ak-Bulak Voyage | B8: 2026-06 | C8: -610056.98 | D8: -326732.13 | E8: 283324.85 | F8: 1171565.3 | G8: 888240.41 | H8: -283324.85 | I8: 561508.28 | J8: 561508.28 | K8: 0 | L8: FALSE | M8: 0 | N8: =ROUND((J8-I8)-(K8+E8+H8),4)
A9: Ak-Bulak Voyage | B9: 2026-07 | C9: -326732.13 | D9: -377925.16 | E9: -51193.03 | F9: 888240.41 | G9: 939433.44 | H9: 51193.03 | I9: 561508.28 | J9: 561508.28 | K9: 5.8207661e-11 | L9: FALSE | M9: 0 | N9: =ROUND((J9-I9)-(K9+E9+H9),4)
A10: Ala-Too Travel | B10: 2026-01 | C10: 0 | D10: -147353.8 | E10: -147353.8 | F10: -3233430.5 | G10: -3086076.7 | H10: 147353.8 | I10: -3233430.5 | J10: -3233430.5 | K10: 0 | L10: FALSE | M10: 0 | N10: =ROUND((J10-I10)-(K10+E10+H10),4)
A11: Ala-Too Travel | B11: 2026-02 | C11: -147353.8 | D11: -266377.05 | E11: -119023.25 | F11: -3086076.7 | G11: -2967053.4 | H11: 119023.25 | I11: -3233430.5 | J11: -3233430.5 | K11: 0 | L11: FALSE | M11: 0 | N11: =ROUND((J11-I11)-(K11+E11+H11),4)
A12: Ala-Too Travel | B12: 2026-03 | C12: -266377.05 | D12: -1072376.2 | E12: -805999.16 | F12: -2967053.4 | G12: -2161054.3 | H12: 805999.16 | I12: -3233430.5 | J12: -3233430.5 | K12: 0 | L12: FALSE | M12: 0 | N12: =ROUND((J12-I12)-(K12+E12+H12),4)
A13: Ala-Too Travel | B13: 2026-04 | C13: -1072376.2 | D13: -1004260.1 | E13: 68116.08 | F13: -2161054.3 | G13: -2229170.4 | H13: -68116.08 | I13: -3233430.5 | J13: -3233430.5 | K13: -1.1641532e-10 | L13: FALSE | M13: 0 | N13: =ROUND((J13-I13)-(K13+E13+H13),4)
A14: Ala-Too Travel | B14: 2026-05 | C14: -1004260.1 | D14: -563010.87 | E14: 441249.26 | F14: -2229170.4 | G14: -2670419.6 | H14: -441249.26 | I14: -3233430.5 | J14: -3233430.5 | K14: 0 | L14: FALSE | M14: 0 | N14: =ROUND((J14-I14)-(K14+E14+H14),4)
A15: Ala-Too Travel | B15: 2026-06 | C15: -563010.87 | D15: -434234.69 | E15: 128776.18 | F15: -2670419.6 | G15: -2831462.3 | H15: -161042.72 | I15: -3233430.5 | J15: -3265697 | K15: 0 | L15: FALSE | M15: 0 | N15: =ROUND((J15-I15)-(K15+E15+H15),4)
... A679: Эсенбекова Айгуль Нурбекевна | B679: 2026-07 | C679: -10487.26 | D679: -312903.7 | E679: -302416.44 | F679: -435101.4 | G679: -135830.36 | H679: 299271.04 | I679: -445588.66 | J679: -448734.06 | K679: 0 | L679: FALSE | M679: 0 | N679: =ROUND((J679-I679)-(K679+E679+H679),4)

Sheet Расхождения
A1: Расхождения по группам билетов (1,792 строк — найденные случаи с источником и уверенностью, а не «ошибки»)
A2: Уверенность: A — подтверждено вторым источником; B — правдоподобная гипотеза; C — данных недостаточно.
A3: ID | B3: Субагент | C3: Билеты | D3: Тип | E3: Источник ошибки | F3: Уверенность | G3: Сумма 1С | H3: Сумма ETM | I3: Сумма реестра | J3: Остаток 1С+ETM | K3: Дата ETM | L3: Дата 1С | M3: Паттерн суммы | N3: Кто проверяет | O3: Сотрудник реестра | P3: Что произошло | Q3: ETM txn
A4: G05983 | B4: БАЙТУР ТУРИЗМ | C4: 2559102147|2559102148|2559102151|2559102154 | D4: Есть в ETM, нет в 1С | E4: 1С | F4: A | G4: 0 | H4: -197836 | I4: 2000 | J4: -197836 | K4: 46129.444 | N4: Бухгалтер 1С | O4: k.dzhumaev|n.abdyldaeva | P4: Списание есть в ETM и продажа в реестре, но в 1С нет реализации по этим билетам — счёт не выставлен | Q4: 57212874,57212913,57212845,57212859
A5: G01740 | B5: Karakol Express | C5: 2476319698|2476319699|2476319700|2476319702 | D5: Сумма не сходится | E5: 1С | F5: A | G5: 137827.2 | H5: -317827.2 | I5: 317827.2 | J5: -180000 | K5: 46198.337 | L5: 46198 | M5: TRANSPOSITION | N5: Бухгалтер 1С | O5: d.mambetova | P5: Реестр (317,827.20) совпадает с ETM (317,827.20), а в 1С 137,827.20: неверная сумма в 1С | Q5: 57401206,57401176,57401199,57401164
A6: G09168 | B6: ИССЫК ТРИП | C6: 2461885824|2461885826|2461885828 | D6: Сумма не сходится | E6: 1С | F6: A | G6: 130386 | H6: -310386 | I6: 310386 | J6: -180000 | K6: 46220.803 | L6: 46220 | M6: TRANSPOSITION | N6: Бухгалтер 1С | O6: d.mambetova | P6: Реестр (310,386.00) совпадает с ETM (310,386.00), а в 1С 130,386.00: неверная сумма в 1С | Q6: 57467395
A7: G05669 | B7: Ак-Куу Тур | C7: 2559099449|2559099450 | D7: Сумма не сходится | E7: 1С | F7: A | G7: 133571.72 | H7: -313571.72 | I7: 313571.82 | J7: -180000 | K7: 46219.342 | L7: 46219 | M7: TRANSPOSITION | N7: Бухгалтер 1С | O7: k.dzhumaev | P7: Реестр (313,571.82) совпадает с ETM (313,571.72), а в 1С 133,571.72: неверная сумма в 1С | Q7: 57463685,57463705
A8: G00258 | B8: Aylana Tour | C8: 2559101779|2559101780|2559101783 | D8: Есть в ETM, нет в 1С | E8: 1С | F8: A | G8: 0 | H8: -163943.25 | J8: -163943.25 | K8: 46217.372 | N8: Бухгалтер 1С | P8: Списание есть в ETM, но в 1С нет реализации по этим билетам — счёт не выставлен | Q8: 57458399
A9: G13883 | B9: ТЯНЬ-ШАНЬ ЭКСПРЕСС | C9: 2416943100|2416943101|2416943104 | D9: Есть в ETM, нет в 1С | E9: 1С | F9: A | G9: 0 | H9: -144706.56 | I9: 144706.56 | J9: -144706.56 | K9: 46194.418 | N9: Бухгалтер 1С | O9: g.omurbekova | P9: Списание есть в ETM и продажа в реестре, но в 1С нет реализации по этим билетам — счёт не выставлен | Q9: 57386616,57386643,57386599
A10: G05473 | B10: Ак-Куу Тур | C10: 2416944535|2416944536|2416944539 | D10: Есть в ETM, нет в 1С | E10: 1С | F10: A | G10: 0 | H10: -138159.9 | I10: 138159.9 | J10: -138159.9 | K10: 46108.459 | N10: Бухгалтер 1С | O10: b.isakov | P10: Списание есть в ETM и продажа в реестре, но в 1С нет реализации по этим билетам — счёт не выставлен | Q10: 57175913,57175908,57175910
A11: G13979 | B11: ТЯНЬ-ШАНЬ ЭКСПРЕСС | C11: 2559103101|2559103102|2559103105 | D11: Есть в ETM, нет в 1С | E11: 1С | F11: A | G11: 0 | H11: -132888.24 | I11: 132888.26 | J11: -132888.24 | K11: 46127.463 | N11: Бухгалтер 1С | O11: d.mambetova | P11: Списание есть в ETM и продажа в реестре, но в 1С нет реализации по этим билетам — счёт не выставлен | Q11: 57209313,57209349,57209331
A12: G03114 | B12: SkyWay Travel | C12: 2461884640|2461884642|2461884643 | D12: Есть в ETM, нет в 1С | E12: 1С | F12: A | G12: 0 | H12: -130356 | I12: 130356 | J12: -130356 | K12: 46089.339 | N12: Бухгалтер 1С | O12: n.abdyldaeva | P12: Списание есть в ETM и продажа в реестре, но в 1С нет реализации по этим билетам — счёт не выставлен | Q12: 57132455,57132492,57132468
A13: G13070 | B13: Сатар уулу Санжар | C13: 2460733285|2460733286|2460733289 | D13: Есть в реестре и 1С, нет в ETM | E13: Бот ETM | F13: A | G13: 129948 | H13: 0 | I13: 129948 | J13: 129948 | L13: 46096 | N13: Разработчик/поддержка бота ETM | O13: b.isakov | P13: Продажа есть в реестре и в 1С, но бот не перенёс её на баланс ETM — списания нет
A14: G01404 | B14: Karakol Express | C14: 2460732939|2460732941|2460732944|2460732945 | D14: Есть в ETM, нет в 1С | E14: 1С | F14: A | G14: 0 | H14: -127788 | I14: 127788 | J14: -127788 | K14: 46185.558 | N14: Бухгалтер 1С | O14: n.abdyldaeva | P14: Списание есть в ETM и продажа в реестре, но в 1С нет реализации по этим билетам — счёт не выставлен | Q14: 57360780,57360839,57360827,57360818
A15: G12266 | B15: САЛАМ ЭЙР | C15: 2416941997|2416942000 | D15: Есть в ETM, нет в 1С | E15: 1С | F15: A | G15: 0 | H15: -127600.2 | I15: 127600.2 | J15: -127600.2 | K15: 46208.551 | N15: Бухгалтер 1С | O15: d.mambetova | P15: Списание есть в ETM и продажа в реестре, но в 1С нет реализации по этим билетам — счёт не выставлен | Q15: 57430999,57430973
A16: G04364 | B16: Абдылда уулу Б. | C16: 2461883509|2461883511|2461883513|2461883514 | D16: Есть в ETM, нет в 1С | E16: 1С | F16: A | G16: 0 | H16: -126240 | I16: 126240 | J16: -126240 | K16: 46166.606 | N16: Бухгалтер 1С | O16: a.toktosunova | P16: Списание есть в ETM и продажа в реестре, но в 1С нет реализации по этим билетам — счёт не выставлен | Q16: 57313272
A17: G10485 | B17: Манас Тревел | C17: 2559102575|2559102576|2559102578 | D17: Есть в реестре и 1С, нет в ETM | E17: Бот ETM | F17: A | G17: 125193.84 | H17: 0 | I17: 125193.84 | J17: 125193.84 | L17: 46148 | N17: Разработчик/поддержка бота ETM | O17: a.toktosunova | P17: Продажа есть в реестре и в 1С, но бот не перенёс её на баланс ETM — списания нет
A18: G14220 | B18: Урматова Айпери Нурбековна | C18: 2552671225|2552671226 | D18: Есть в реестре и 1С, нет в ETM | E18: Бот ETM | F18: A | G18: 117615.24 | H18: 0 | I18: 117615.25 | J18: 117615.24 | L18: 46085 | N18: Разработчик/поддержка бота ETM | O18: d.mambetova | P18: Продажа есть в реестре и в 1С, но бот не перенёс её на баланс ETM — списания нет
A19: G09824 | B19: Кенешова Чолпон Таалайовна | C19: 2416941910|2416941911 | D19: Есть в реестре и 1С, нет в ETM | E19: Бот ETM | F19: A | G19: 116129.76 | H19: 0 | I19: 116129.75 | J19: 116129.76 | L19: 46052 | N19: Разработчик/поддержка бота ETM | O19: d.mambetova | P19: Продажа есть в реестре и в 1С, но бот не перенёс её на баланс ETM — списания нет
A20: G05815 | B20: Асанов Кубат Чынаревич | C20: 2416943380|2416943382 | D20: Есть в ETM, нет в 1С | E20: 1С | F20: A | G20: 0 | H20: -115067.94 | J20: -115067.94 | K20: 46179.663 | N20: Бухгалтер 1С | P20: Списание есть в ETM, но в 1С нет реализации по этим билетам — счёт не выставлен | Q20: 57346685
A21: G07555 | B21: Жолчу кызы А. | C21: 2552667333|2552667336 | D21: Есть в ETM, нет в 1С | E21: 1С | F21: A | G21: 0 | H21: -110088.8 | I21: 2023.2 | J21: -110088.8 | K21: 46215.563 | N21: Бухгалтер 1С | O21: a.toktosunova|k.dzhumaev | P21: Списание есть в ETM и продажа в реестре, но в 1С нет реализации по этим билетам — счёт не выставлен | Q21: 57452130
A22: G10423 | B22: Манас Тревел | C22: 2552669638|2552669640|2552669642 | D22: Есть в ETM, нет в 1С | E22: 1С | F22: A | G22: 0 | H22: -106792.92 | I22: 106792.92 | J22: -106792.92 | K22: 46089.393 | N22: Бухгалтер 1С | O22: e.satarov | P22: Списание есть в ETM и продажа в реестре, но в 1С нет реализации по этим билетам — счёт не выставлен | Q22: 57132122
A23: G04442 | B23: Абдылда уулу Б. | C23: 2476319155|2476319157|2476319158|2476319159 | D23: Есть в реестре и 1С, нет в ETM | E23: Бот ETM | F23: A | G23: 105761.04 | H23: 0 | I23: 105761.04 | J23: 105761.04 | L23: 46099 | N23: Разработчик/поддержка бота ETM | O23: k.dzhumaev | P23: Продажа есть в реестре и в 1С, но бот не перенёс её на баланс ETM — списания нет
A24: G04751 | B24: Ак-Куу Авиа | C24: 2416942350|2416942353|2416942356|2416942357 | D24: Есть в реестре и 1С, нет в ETM | E24: Бот ETM | F24: A | G24: 104833.2 | H24: 0 | I24: 104833.2 | J24: 104833.2 | L24: 46035 | N24: Разработчик/поддержка бота ETM | O24: a.toktosunova | P24: Продажа есть в реестре и в 1С, но бот не перенёс её на баланс ETM — списания нет
A25: G04540 | B25: Абдылда уулу Б. | C25: 2559103835|2559103836 | D25: Есть в реестре и 1С, нет в ETM | E25: Бот ETM | F25: A | G25: 98842.08 | H25: 0 | I25: 98842.08 | J25: 98842.08 | L25: 46097 | N25: Разработчик/поддержка бота ETM | O25: a.toktosunova | P25: Продажа есть в реестре и в 1С, но бот не перенёс её на баланс ETM — списания нет
A26: G09676 | B26: Кадырова Айнура Жумабекевна | C26: 2460736923|2460736926|2460736927 | D26: Есть в ETM, нет в 1С | E26: 1С | F26: A | G26: 0 | H26: -97458 | I26: 97458 | J26: -97458 | K26: 46148.78 | N26: Бухгалтер 1С | O26: k.dzhumaev | P26: Списание есть в ETM и продажа в реестре, но в 1С нет реализации по этим билетам — счёт не выставлен | Q26: 57259064,57259120,57259100
A27: G13427 | B27: Сатарова А. О. | C27: 2476314998|2476315000|2476315003 | D27: Есть в реестре и 1С, нет в ETM | E27: Бот ETM | F27: A | G27: 96800.94 | H27: 0 | I27: 96800.94 | J27: 96800.94 | L27: 46102 | N27: Разработчик/поддержка бота ETM | O27: b.isakov | P27: Продажа есть в реестре и в 1С, но бот не перенёс её на баланс ETM — списания нет
A28: G10159 | B28: Манас Вояж | C28: 2552671660|2552671662|2552671665 | D28: Есть в ETM, нет в 1С | E28: 1С | F28: A | G28: 0 | H28: -96385.29 | I28: 96385.298 | J28: -96385.29 | K28: 46114.477 | N28: Бухгалтер 1С | O28: d.mambetova | P28: Списание есть в ETM и продажа в реестре, но в 1С нет реализации по этим билетам — счёт не выставлен | Q28: 57186857,57186863,57186859
A29: G02612 | B29: SkyWay Travel | C29: 2459527020|2459527022|2459527024 | D29: Есть в реестре и 1С, нет в ETM | E29: Бот ETM | F29: A | G29: 95907 | H29: 0 | I29: 95907 | J29: 95907 | L29: 46049 | N29: Разработчик/поддержка бота ETM | O29: g.omurbekova | P29: Продажа есть в реестре и в 1С, но бот не перенёс её на баланс ETM — списания нет
A30: G04713 | B30: Абдыраманова Д. А. | C30: 2552670154|2552670155|2552670158 | D30: Есть в ETM, нет в 1С | E30: 1С | F30: A | G30: 0 | H30: -95039.82 | I30: 95039.82 | J30: -95039.82 | K30: 46230.344 | N30: Бухгалтер 1С | O30: b.isakov | P30: Списание есть в ETM и продажа в реестре, но в 1С нет реализации по этим билетам — счёт не выставлен | Q30: 57492130,57492158,57492136
A31: G09913 | B31: МУРАС ТРИП | C31: 2416943912|2416943914 | D31: Сумма не сходится | E31: 1С | F31: A | G31: -80610.18 | H31: -14225.32 | I31: 14225.32 | J31: -94835.5 | K31: 46214.511 | L31: 46225 | N31: Бухгалтер 1С | O31: b.isakov|e.satarov | P31: Реестр (14,225.32) совпадает с ETM (14,225.32), а в 1С -80,610.18: неверная сумма в 1С | Q31: 57450691,57450661,57477805
A32: G02341 | B32: SkyWay Travel | C32: 2416944456|2416944459 | D32: Сумма не сходится | E32: 1С | F32: A | G32: -70885.77 | H32: -23628.59 | I32: 23628.58 | J32: -94514.36 | K32: 46079.624 | L32: 46136 | N32: Бухгалтер 1С | O32: n.abdyldaeva|r.sydykov | P32: Реестр (23,628.58) совпадает с ETM (23,628.59), а в 1С -70,885.77: неверная сумма в 1С | Q32: 57110804,57110829,57225878
A33: G14715 | B33: ЫЙЫК ЭКСПРЕСС | C33: 2416942558|2416942561 | D33: Есть в реестре и 1С, нет в ETM | E33: Бот ETM | F33: A | G33: 94019.5 | H33: 0 | I33: 94019.5 | J33: 94019.5 | L33: 46148 | N33: Разработчик/поддержка бота ETM | O33: k.dzhumaev | P33: Продажа есть в реестре и в 1С, но бот не перенёс её на баланс ETM — списания нет
A34: G09258 | B34: ИССЫК ТРИП | C34: 2552667309|2552667312 | D34: Есть в реестре и 1С, нет в ETM | E34: Бот ETM | F34: A | G34: 93237.8 | H34: 0 | I34: 93237.8 | J34: 93237.8 | L34: 46159 | N34: Разработчик/поддержка бота ETM | O34: b.isakov | P34: Продажа есть в реестре и в 1С, но бот не перенёс её на баланс ETM — списания нет
A35: G13576 | B35: Сыдыков С. У. | C35: 2552670969|2552670970|2552670973 | D35: Есть в реестре и 1С, нет в ETM | E35: Бот ETM | F35: A | G35: 91517.13 | H35: 0 | I35: 91517.137 | J35: 91517.13 | L35: 46028 | N35: Разработчик/поддержка бота ETM | O35: k.dzhumaev | P35: Продажа есть в реестре и в 1С, но бот не перенёс её на баланс ETM — списания нет
A36: G08989 | B36: ИССЫК ТРИП | C36: 2459526893|2459526894 | D36: Есть в ETM, нет в 1С | E36: 1С | F36: A | G36: 0 | H36: -89440 | I36: 89440 | J36: -89440 | K36: 46151.406 | N36: Бухгалтер 1С | O36: n.abdyldaeva | P36: Списание есть в ETM и продажа в реестре, но в 1С нет реализации по этим билетам — счёт не выставлен | Q36: 57266763,57266742
A37: G06813 | B37: Джолдошова Салтанат Сатаревна | C37: 2559099104|2559099107 | D37: Есть в ETM, нет в 1С | E37: 1С | F37: A | G37: 0 | H37: -89279.04 | I37: 1000 | J37: -89279.04 | K37: 46070.639 | N37: Бухгалтер 1С | O37: b.isakov|d.mambetova | P37: Списание есть в ETM и продажа в реестре, но в 1С нет реализации по этим билетам — счёт не выставлен | Q37: 57094267,57094265
A38: G12224 | B38: САЛАМ ВОЯЖ | C38: 2459528839|2459528840 | D38: Сумма не сходится | E38: Бот ETM | F38: A | G38: 48998.4 | H38: 40089.6 | I38: 48998.4 | J38: 89088 | K38: 46177.491 | L38: 46133 | N38: Разработчик/поддержка бота ETM | O38: b.isakov|g.omurbekova | P38: Реестр (48,998.40) совпадает с 1С (48,998.40), а в ETM -40,089.60: бот перенёс неверную сумму | Q38: 57339940
A39: G07877 | B39: ИП Асанов К. Б. | C39: 2552668100|2552668103|2552668104 | D39: Есть в ETM, нет в 1С | E39: 1С | F39: A | G39: 0 | H39: -87873.87 | I39: 87873.878 | J39: -87873.87 | K39: 46179.546 | N39: Бухгалтер 1С | O39: b.isakov | P39: Списание есть в ETM и продажа в реестре, но в 1С нет реализации по этим билетам — счёт не выставлен | Q39: 57345966,57345926,57345964
A40: G10319 | B40: Манас Тревел | C40: 2460736416|2460736417 | D40: Есть в ETM, нет в 1С | E40: 1С | F40: A | G40: 0 | H40: -87744 | I40: 87744 | J40: -87744 | K40: 46039.666 | N40: Бухгалтер 1С | O40: d.mambetova | P40: Списание есть в ETM и продажа в реестре, но в 1С нет реализации по этим билетам — счёт не выставлен | Q40: 57034828,57034817
A41: G14186 | B41: Урматова Айпери Нурбековна | C41: 2461882937|2461882939 | D41: Есть в ETM, нет в 1С | E41: 1С | F41: A | G41: 0 | H41: -86718 | I41: 86718 | J41: -86718 | K41: 46038.679 | N41: Бухгалтер 1С | O41: d.mambetova | P41: Списание есть в ETM и продажа в реестре, но в 1С нет реализации по этим билетам — счёт не выставлен | Q41: 57031783,57031764
A42: G11484 | B42: ОсОО Кара-Кол Трип | C42: 2416944269|2416944270|2416944273 | D42: Есть в ETM, нет в 1С | E42: 1С | F42: A | G42: 0 | H42: -80770.92 | I42: 80770.92 | J42: -80770.92 | K42: 46228.402 | N42: Бухгалтер 1С | O42: r.sydykov | P42: Списание есть в ETM и продажа в реестре, но в 1С нет реализации по этим билетам — счёт не выставлен | Q42: 57487196,57487161,57487194
A43: G13270 | B43: Сатар уулу Санжар | C43: 2552667874|2552667877 | D43: Сумма не сходится | E43: 1С | F43: A | G43: 105955.44 | H43: -26488.86 | I43: 26488.87 | J43: 79466.58 | K43: 46166.609 | L43: 46166 | N43: Бухгалтер 1С | O43: g.omurbekova|r.sydykov | P43: Реестр (26,488.87) совпадает с ETM (26,488.86), а в 1С 105,955.44: неверная сумма в 1С | Q43: 57312406,57312400,57337869
A44: G10198 | B44: Манас Тревел | C44: 2416944813|2416944816|2416944819 | D44: Есть в ETM, нет в 1С | E44: 1С | F44: A | G44: 0 | H44: -75414.36 | I44: 75414.345 | J44: -75414.36 | K44: 46141.368 | N44: Бухгалтер 1С | O44: r.sydykov | P44: Списание есть в ETM и продажа в реестре, но в 1С нет реализации по этим билетам — счёт не выставлен | Q44: 57237738,57237704,57237674
A45: G01972 | B45: Karakol Express | C45: 2559103448|2559103451 | D45: Есть в реестре и 1С, нет в ETM | E45: Бот ETM | F45: A | G45: 75381.06 | H45: 0 | I45: 75381.05 | J45: 75381.06 | L45: 46223 | N45: Разработчик/поддержка бота ETM | O45: g.omurbekova | P45: Продажа есть в реестре и в 1С, но бот не перенёс её на баланс ETM — списания нет
A46: G08891 | B46: ИССЫК ТРИП | C46: 2416944487|2416944490 | D46: Есть в ETM, нет в 1С | E46: 1С | F46: A | G46: 0 | H46: -74579.92 | I46: 74579.92 | J46: -74579.92 | K46: 46096.394 | N46: Бухгалтер 1С | O46: a.toktosunova | P46: Списание есть в ETM и продажа в реестре, но в 1С нет реализации по этим билетам — счёт не выставлен | Q46: 57149412,57149441
A47: G11681 | B47: ОсОО Кок-Жайык Вояж | C47: 2461882909|2461882912|2461882915 | D47: Есть в реестре и 1С, нет в ETM | E47: Бот ETM | F47: A | G47: 73794 | H47: 0 | I47: 73794 | J47: 73794 | L47: 46141 | N47: Разработчик/поддержка бота ETM | O47: g.omurbekova | P47: Продажа есть в реестре и в 1С, но бот не перенёс её на баланс ETM — списания нет
A48: G09272 | B48: ИССЫК ТРИП | C48: 2552668397|2552668399|2552668401 | D48: Есть в ETM, нет в 1С | E48: 1С | F48: A | G48: 0 | H48: -73454.07 | I48: 900 | J48: -73454.07 | K48: 46104.524 | N48: Бухгалтер 1С | O48: e.satarov|g.omurbekova | P48: Списание есть в ETM и продажа в реестре, но в 1С нет реализации по этим билетам — счёт не выставлен | Q48: 57165464
A49: G01015 | B49: Jailoo Trip | C49: 2476314807|2476314810|2476314813|2476314816 | D49: Есть в реестре и 1С, нет в ETM | E49: Бот ETM | F49: A | G49: 73085.04 | H49: 0 | I49: 73085.04 | J49: 73085.04 | L49: 46153 | N49: Разработчик/поддержка бота ETM | O49: k.dzhumaev | P49: Продажа есть в реестре и в 1С, но бот не перенёс её на баланс ETM — списания нет
A50: G07949 | B50: ИП Бейшенова Д. О. | C50: 2460735390|2460735392|2460735394 | D50: Есть в реестре и 1С, нет в ETM | E50: Бот ETM | F50: A | G50: 72945 | H50: 0 | I50: 72945 | J50: 72945 | L50: 46108 | N50: Разработчик/поддержка бота ETM | O50: n.abdyldaeva | P50: Продажа есть в реестре и в 1С, но бот не перенёс её на баланс ETM — списания нет
A51: G01783 | B51: Karakol Express | C51: 2552668375|2552668376|2552668378 | D51: Есть в реестре и 1С, нет в ETM | E51: Бот ETM | F51: A | G51: 72109.11 | H51: 0 | I51: 72109.102 | J51: 72109.11 | L51: 46034 | N51: Разработчик/поддержка бота ETM | O51: b.isakov | P51: Продажа есть в реестре и в 1С, но бот не перенёс её на баланс ETM — списания нет
A52: G09990 | B52: МУРАС ТРИП | C52: 2552671980|2552671981 | D52: Есть в ETM, нет в 1С | E52: 1С | F52: A | G52: 0 | H52: -72080.34 | I52: 72080.335 | J52: -72080.34 | K52: 46137.748 | N52: Бухгалтер 1С | O52: b.isakov | P52: Списание есть в ETM и продажа в реестре, но в 1С нет реализации по этим билетам — счёт не выставлен | Q52: 57229065,57229043
A53: G00205 | B53: Aylana Tour | C53: 2461885523 | D53: Сумма не сходится | E53: 1С | F53: A | G53: 19284 | H53: -91284 | I53: 91284 | J53: -72000 | K53: 46148.775 | L53: 46148 | M53: TRANSPOSITION | N53: Бухгалтер 1С | O53: b.isakov | P53: Реестр (91,284.00) совпадает с ETM (91,284.00), а в 1С 19,284.00: неверная сумма в 1С | Q53: 57259560
A54: G02367 | B54: SkyWay Travel | C54: 2416945181|2416945183 | D54: Есть в реестре и 1С, нет в ETM | E54: Бот ETM | F54: A | G54: 71673.88 | H54: 0 | I54: 71673.88 | J54: 71673.88 | L54: 46122 | N54: Разработчик/поддержка бота ETM | O54: b.isakov | P54: Продажа есть в реестре и в 1С, но бот не перенёс её на баланс ETM — списания нет
A55: G03650 | B55: SkyWay Travel | C55: 2559100258|2559100260|2559100261|2559100263 | D55: Есть в ETM, нет в 1С | E55: 1С | F55: A | G55: 0 | H55: -71250 | J55: -71250 | K55: 46106.674 | N55: Бухгалтер 1С | P55: Списание есть в ETM, но в 1С нет реализации по этим билетам — счёт не выставлен | Q55: 57170155
A56: G06722 | B56: Джолдошова Салтанат Сатаревна | C56: 2476315088|2476315091|2476315092 | D56: Есть в ETM, нет в 1С | E56: 1С | F56: A | G56: 0 | H56: -68921.58 | I56: 68921.58 | J56: -68921.58 | K56: 46188.722 | N56: Бухгалтер 1С | O56: n.abdyldaeva | P56: Списание есть в ETM и продажа в реестре, но в 1С нет реализации по этим билетам — счёт не выставлен | Q56: 57368832
A57: G06997 | B57: Жибек Авиакасса | C57: 2476314006|2476314008 | D57: Есть в ETM, нет в 1С | E57: 1С | F57: A | G57: 0 | H57: -67981.28 | I57: 2653.28 | J57: -67981.28 | K57: 46046.385 | N57: Бухгалтер 1С | O57: g.omurbekova|n.abdyldaeva | P57: Списание есть в ETM и продажа в реестре, но в 1С нет реализации по этим билетам — счёт не выставлен | Q57: 57049163,57049167
A58: G10466 | B58: Манас Тревел | C58: 2559100195|2559100197|2559100199 | D58: Есть в ETM, нет в 1С | E58: 1С | F58: A | G58: 0 | H58: -67603.2 | I58: 67603.2 | J58: -67603.2 | K58: 46196.552 | N58: Бухгалтер 1С | O58: k.dzhumaev | P58: Списание есть в ETM и продажа в реестре, но в 1С нет реализации по этим билетам — счёт не выставлен | Q58: 57392669
A59: G13494 | B59: Сатарова Жылдыз Жумабековна | C59: 2461884988|2461884990 | D59: Есть в ETM, нет в 1С | E59: 1С | F59: A | G59: 0 | H59: -66482 | I59: 66482 | J59: -66482 | K59: 46114.463 | N59: Бухгалтер 1С | O59: a.toktosunova | P59: Списание есть в ETM и продажа в реестре, но в 1С нет реализации по этим билетам — счёт не выставлен | Q59: 57186849
A60: G06551 | B60: Джолдошова Салтанат Сатаревна | C60: 2416946213 | D60: Есть в ETM, нет в 1С | E60: 1С | F60: A | G60: 0 | H60: -66111.38 | J60: -66111.38 | K60: 46214.412 | N60: Бухгалтер 1С | P60: Списание есть в ETM, но в 1С нет реализации по этим билетам — счёт не выставлен | Q60: 57451749
A61: G03305 | B61: SkyWay Travel | C61: 2476318215|2476318217|2476318219 | D61: Сумма не сходится | E61: 1С | F61: A | G61: -21756.29 | H61: -43512.58 | I61: 43512.58 | J61: -65268.87 | K61: 46121.347 | L61: 46173 | N61: Бухгалтер 1С | O61: a.toktosunova|b.isakov | P61: Реестр (43,512.58) совпадает с ETM (43,512.58), а в 1С -21,756.29: неверная сумма в 1С | Q61: 57198944,57198990,57198979,57330127
A62: G02684 | B62: SkyWay Travel | C62: 2459529278|2459529281 | D62: Есть в ETM, нет в 1С | E62: 1С | F62: A | G62: 0 | H62: -65264 | I62: 65264 | J62: -65264 | K62: 46178.514 | N62: Бухгалтер 1С | O62: g.omurbekova | P62: Списание есть в ETM и продажа в реестре, но в 1С нет реализации по этим билетам — счёт не выставлен | Q62: 57343983,57343982
A63: G01620 | B63: Karakol Express | C63: 2461886049|2461886052 | D63: Есть в реестре и 1С, нет в ETM | E63: Бот ETM | F63: A | G63: 65108 | H63: 0 | I63: 65108 | J63: 65108 | L63: 46200 | N63: Разработчик/поддержка бота ETM | O63: k.dzhumaev | P63: Продажа есть в реестре и в 1С, но бот не перенёс её на баланс ETM — списания нет
A64: G07962 | B64: ИП Бейшенова Д. О. | C64: 2461882228|2461882230 | D64: Есть в ETM, нет в 1С | E64: 1С | F64: A | G64: 0 | H64: -64990 | I64: 64990 | J64: -64990 | K64: 46063.779 | N64: Бухгалтер 1С | O64: d.mambetova | P64: Списание есть в ETM и продажа в реестре, но в 1С нет реализации по этим билетам — счёт не выставлен | Q64: 57082774
A65: G13589 | B65: Сыдыков С. У. | C65: 2559102500|2559102502 | D65: Сумма не сходится | E65: 1С | F65: A | G65: 76437.66 | H65: -11465.65 | I65: 11465.66 | J65: 64972.01 | K65: 46122.56 | L65: 46122 | N65: Бухгалтер 1С | O65: a.toktosunova|g.omurbekova | P65: Реестр (11,465.66) совпадает с ETM (11,465.65), а в 1С 76,437.66: неверная сумма в 1С | Q65: 57200841,57200881,57271171
A66: G11710 | B66: ОсОО Кок-Жайык Вояж | C66: 2476319584|2476319586|2476319588 | D66: Есть в ETM, нет в 1С | E66: 1С | F66: A | G66: 0 | H66: -64800.54 | I66: 0 | J66: -64800.54 | K66: 46107.507 | N66: Бухгалтер 1С | O66: k.dzhumaev|r.sydykov | P66: Списание есть в ETM и продажа в реестре, но в 1С нет реализации по этим билетам — счёт не выставлен | Q66: 57173848,57173844,57173883
A67: G05619 | B67: Ак-Куу Тур | C67: 2476317923 | D67: Сумма не сходится | E67: 1С | F67: A | G67: 18090.11 | H67: -81090.11 | I67: 81090.112 | J67: -63000 | K67: 46215.578 | L67: 46215 | M67: TRANSPOSITION | N67: Бухгалтер 1С | O67: d.mambetova | P67: Реестр (81,090.11) совпадает с ETM (81,090.11), а в 1С 18,090.11: неверная сумма в 1С | Q67: 57453281
A68: G14197 | B68: Урматова Айпери Нурбековна | C68: 2476315613 | D68: Сумма не сходится | E68: Бот ETM | F68: A | G68: 18935.88 | H68: -81935.88 | I68: 18935.88 | J68: -63000 | K68: 46084.624 | L68: 46084 | M68: TRANSPOSITION | N68: Разработчик/поддержка бота ETM | O68: e.satarov | P68: Реестр (18,935.88) совпадает с 1С (18,935.88), а в ETM 81,935.88: бот перенёс неверную сумму | Q68: 57119979
A69: G02321 | B69: SkyWay Travel | C69: 2416943861 | D69: Есть в ETM, нет в 1С | E69: 1С | F69: A | G69: 0 | H69: -62627.9 | I69: 62627.9 | J69: -62627.9 | K69: 46183.791 | N69: Бухгалтер 1С | O69: n.abdyldaeva | P69: Списание есть в ETM и продажа в реестре, но в 1С нет реализации по этим билетам — счёт не выставлен | Q69: 57356861
A70: G06516 | B70: Джолдошова Салтанат Сатаревна | C70: 2416941844 | D70: Есть в реестре и 1С, нет в ETM | E70: Бот ETM | F70: A | G70: 62600.03 | H70: 0 | I70: 62600.025 | J70: 62600.03 | L70: 46108 | N70: Разработчик/поддержка бота ETM | O70: r.sydykov | P70: Продажа есть в реестре и в 1С, но бот не перенёс её на баланс ETM — списания нет
A71: G13664 | B71: ТАЛАС ЛАЙН | C71: 2416946131 | D71: Двойное списание в ETM | E71: Бот ETM | F71: A | G71: 62508.38 | H71: -125016.76 | I71: 62508.375 | J71: -62508.38 | K71: 46117.792 | L71: 46117 | N71: Разработчик/поддержка бота ETM | O71: n.abdyldaeva | P71: В ETM 1 лишн. списание(й) одного билета на 62,508.38; без дубля сумма совпадает с 1С | Q71: 57192041,57192059
A72: G10189 | B72: Манас Тревел | C72: 2416943674|2416943675 | D72: Есть в реестре и 1С, нет в ETM | E72: Бот ETM | F72: A | G72: 60659.64 | H72: 0 | I72: 60659.65 | J72: 60659.64 | L72: 46167 | N72: Разработчик/поддержка бота ETM | O72: d.mambetova | P72: Продажа есть в реестре и в 1С, но бот не перенёс её на баланс ETM — списания нет
A73: G06134 | B73: Байтур Трип | C73: 2552672508 | D73: Есть в ETM, нет в 1С | E73: 1С | F73: A | G73: 0 | H73: -59655.06 | I73: 59655.062 | J73: -59655.06 | K73: 46107.489 | N73: Бухгалтер 1С | O73: b.isakov | P73: Списание есть в ETM и продажа в реестре, но в 1С нет реализации по этим билетам — счёт не выставлен | Q73: 57173812
A74: G01898 | B74: Karakol Express | C74: 2559099861|2559099864 | D74: Есть в ETM, нет в 1С | E74: 1С | F74: A | G74: 0 | H74: -59101.26 | I74: 210.18 | J74: -59101.26 | K74: 46086.594 | N74: Бухгалтер 1С | O74: k.dzhumaev|r.sydykov | P74: Списание есть в ETM и продажа в реестре, но в 1С нет реализации по этим билетам — счёт не выставлен | Q74: 57124965,57125001
A75: G15063 | B75: Ыйык Тур | C75: 2460735108|2460735111|2460735114 | D75: Есть в реестре и 1С, нет в ETM | E75: Бот ETM | F75: A | G75: 58449 | H75: 0 | I75: 58449 | J75: 58449 | L75: 46113 | N75: Разработчик/поддержка бота ETM | O75: r.sydykov | P75: Продажа есть в реестре и в 1С, но бот не перенёс её на баланс ETM — списания нет
A76: G09887 | B76: Кенешова Чолпон Таалайовна | C76: 2552669448 | D76: Есть в ETM, нет в 1С | E76: 1С | F76: A | G76: 0 | H76: -58267.82 | I76: 58267.82 | J76: -58267.82 | K76: 46223.609 | N76: Бухгалтер 1С | O76: a.toktosunova | P76: Списание есть в ETM и продажа в реестре, но в 1С нет реализации по этим билетам — счёт не выставлен | Q76: 57473508
A77: G07416 | B77: Жибек Эйр | C77: 2559099149|2559099151 | D77: Сумма не сходится | E77: 1С | F77: A | G77: -21783.8 | H77: -36306.32 | I77: 36306.32 | J77: -58090.12 | K77: 46170.563 | L77: 46191 | N77: Бухгалтер 1С | O77: g.omurbekova|n.abdyldaeva | P77: Реестр (36,306.32) совпадает с ETM (36,306.32), а в 1С -21,783.80: неверная сумма в 1С | Q77: 57322915,57322912,57377460
A78: G13357 | B78: Сатар уулу Санжар | C78: 2559102001 | D78: Есть в ETM, нет в 1С | E78: 1С | F78: A | G78: 0 | H78: -57648.66 | I78: 57648.66 | J78: -57648.66 | K78: 46069.63 | N78: Бухгалтер 1С | O78: n.abdyldaeva | P78: Списание есть в ETM и продажа в реестре, но в 1С нет реализации по этим билетам — счёт не выставлен | Q78: 57093408
A79: G01332 | B79: Karakol Express | C79: 2459529682|2459529684|2459529687 | D79: Есть в ETM, нет в 1С | E79: 1С | F79: A | G79: 0 | H79: -57516 | I79: 57516 | J79: -57516 | K79: 46088.392 | N79: Бухгалтер 1С | O79: d.mambetova | P79: Списание есть в ETM и продажа в реестре, но в 1С нет реализации по этим билетам — счёт не выставлен | Q79: 57130243,57130225,57130201
A80: G02184 | B80: Silk Route Air | C80: 2476314123|2476314126|2476314127 | D80: Есть в ETM, нет в 1С | E80: 1С | F80: A | G80: 0 | H80: -57223.11 | I80: 57223.11 | J80: -57223.11 | K80: 46184.521 | N80: Бухгалтер 1С | O80: n.abdyldaeva | P80: Списание есть в ETM и продажа в реестре, но в 1С нет реализации по этим билетам — счёт не выставлен | Q80: 57358528,57358527,57358544
A81: G03800 | B81: Steppe Travel | C81: 2416941084 | D81: Двойное списание в ETM | E81: Бот ETM | F81: A | G81: 56402.58 | H81: -112805.16 | I81: 56402.58 | J81: -56402.58 | K81: 46105.384 | L81: 46105 | N81: Разработчик/поддержка бота ETM | O81: b.isakov | P81: В ETM 1 лишн. списание(й) одного билета на 56,402.58; без дубля сумма совпадает с 1С | Q81: 57167793,57167775
A82: G02069 | B82: Nomad Trip | C82: 2416945048|2416945049 | D82: Есть в ETM, нет в 1С | E82: 1С | F82: A | G82: 0 | H82: -56055.46 | I82: 56055.45 | J82: -56055.46 | K82: 46142.441 | N82: Бухгалтер 1С | O82: a.toktosunova | P82: Списание есть в ETM и продажа в реестре, но в 1С нет реализации по этим билетам — счёт не выставлен | Q82: 57240366,57240402
A83: G12964 | B83: Сатар уулу Санжар | C83: 2420846300|2420846303|2420846306|2420846307 | D83: Сумма не сходится | E83: 1С | F83: A | G83: 62142.2 | H83: -6214.22 | I83: 6214.2076 | J83: 55927.98 | K83: 46145.48 | L83: 46145 | N83: Бухгалтер 1С | O83: e.satarov|n.abdyldaeva | P83: Реестр (6,214.21) совпадает с ETM (6,214.22), а в 1С 62,142.20: неверная сумма в 1С | Q83: 57248550,57248606,57248574,57248515,57377370
A84: G09875 | B84: Кенешова Чолпон Таалайовна | C84: 2476318678|2476318681 | D84: Есть в ETM, нет в 1С | E84: 1С | F84: A | G84: 0 | H84: -55641.68 | I84: 55641.68 | J84: -55641.68 | K84: 46076.689 | N84: Бухгалтер 1С | O84: b.isakov | P84: Списание есть в ETM и продажа в реестре, но в 1С нет реализации по этим билетам — счёт не выставлен | Q84: 57105416
A85: G06012 | B85: Байтур Трип | C85: 2420844670|2420844672 | D85: Есть в ETM, нет в 1С | E85: 1С | F85: A | G85: 0 | H85: -55607.1 | I85: 55607.107 | J85: -55607.1 | K85: 46072.759 | N85: Бухгалтер 1С | O85: k.dzhumaev | P85: Списание есть в ETM и продажа в реестре, но в 1С нет реализации по этим билетам — счёт не выставлен | Q85: 57097974
A86: G05625 | B86: Ак-Куу Тур | C86: 2476319780|2476319783 | D86: Есть в ETM, нет в 1С | E86: 1С | F86: A | G86: 0 | H86: -55414.32 | I86: 3534.84 | J86: -55414.32 | K86: 46085.413 | N86: Бухгалтер 1С | O86: d.mambetova|e.satarov | P86: Списание есть в ETM и продажа в реестре, но в 1С нет реализации по этим билетам — счёт не выставлен | Q86: 57123848,57123845
A87: G09534 | B87: КУТ ЭЙР | C87: 2552667483 | D87: Есть в ETM, нет в 1С | E87: 1С | F87: A | G87: 0 | H87: -54131.11 | I87: 54131.113 | J87: -54131.11 | K87: 46182.666 | N87: Бухгалтер 1С | O87: n.abdyldaeva | P87: Списание есть в ETM и продажа в реестре, но в 1С нет реализации по этим билетам — счёт не выставлен | Q87: 57353577
A88: G07560 | B88: Жолчу кызы А. | C88: 2552669349|2552669352 | D88: Сумма не сходится | E88: 1С | F88: A | G88: 117618.26 | H88: -171618.26 | I88: 171618.22 | J88: -54000 | K88: 46037.443 | L88: 46037 | M88: TRANSPOSITION | N88: Бухгалтер 1С | O88: d.mambetova | P88: Реестр (171,618.22) совпадает с ETM (171,618.26), а в 1С 117,618.26: неверная сумма в 1С | Q88: 57029306,57029273
A89: G15204 | B89: Ыйык Тур | C89: 2552670417 | D89: Сумма не сходится | E89: 1С | F89: A | G89: 19514.68 | H89: -73514.68 | I89: 73514.752 | J89: -54000 | K89: 46071.58 | L89: 46071 | N89: Бухгалтер 1С | O89: g.omurbekova|k.dzhumaev | P89: Реестр (73,514.75) совпадает с ETM (73,514.68), а в 1С 19,514.68: неверная сумма в 1С | Q89: 57096430,57210034
A90: G07610 | B90: Жумабек кызы Умут | C90: 2420844352 | D90: Сумма не сходится | E90: 1С | F90: A | G90: 17134.7 | H90: -71134.7 | I90: 71134.699 | J90: -54000 | K90: 46174.682 | L90: 46174 | M90: TRANSPOSITION | N90: Бухгалтер 1С | O90: k.dzhumaev | P90: Реестр (71,134.70) совпадает с ETM (71,134.70), а в 1С 17,134.70: неверная сумма в 1С | Q90: 57333138
A91: G10019 | B91: Мамбет уулу Чынгыз | C91: 2420844506 | D91: Сумма не сходится | E91: Бот ETM | F91: A | G91: 17961.84 | H91: -71961.84 | I91: 17961.839 | J91: -54000 | K91: 46100.632 | L91: 46100 | M91: TRANSPOSITION | N91: Разработчик/поддержка бота ETM | O91: b.isakov | P91: Реестр (17,961.84) совпадает с 1С (17,961.84), а в ETM 71,961.84: бот перенёс неверную сумму | Q91: 57157369
A92: G10290 | B92: Манас Тревел | C92: 2460733069|2460733071|2460733072 | D92: Сумма не сходится | E92: 1С | F92: A | G92: 128748 | H92: -182748 | I92: 182748 | J92: -54000 | K92: 46163.364 | L92: 46163 | M92: TRANSPOSITION | N92: Бухгалтер 1С | O92: k.dzhumaev | P92: Реестр (182,748.00) совпадает с ETM (182,748.00), а в 1С 128,748.00: неверная сумма в 1С | Q92: 57303797,57303800,57303814
A93: G11616 | B93: ОсОО Кок-Жайык Вояж | C93: 2416943897 | D93: Сумма не сходится | E93: Бот ETM | F93: A | G93: 17134.8 | H93: -71134.8 | I93: 17134.8 | J93: -54000 | K93: 46091.617 | L93: 46091 | M93: TRANSPOSITION | N93: Разработчик/поддержка бота ETM | O93: a.toktosunova | P93: Реестр (17,134.80) совпадает с 1С (17,134.80), а в ETM 71,134.80: бот перенёс неверную сумму | Q93: 57137639
A94: G11712 | B94: ОсОО Кок-Жайык Вояж | C94: 2552667487|2552667489 | D94: Сумма не сходится | E94: Бот ETM | F94: A | G94: 106201.6 | H94: -160201.6 | I94: 106201.6 | J94: -54000 | K94: 46094.749 | L94: 46094 | M94: TRANSPOSITION | N94: Разработчик/поддержка бота ETM | O94: b.isakov | P94: Реестр (106,201.60) совпадает с 1С (106,201.60), а в ETM 160,201.60: бот перенёс неверную сумму | Q94: 57144670
A95: G00940 | B95: Issyk-Kul Air | C95: 2476317982|2476317984 | D95: Есть в ETM, нет в 1С | E95: 1С | F95: A | G95: 0 | H95: -53883.88 | I95: 53883.88 | J95: -53883.88 | K95: 46063.634 | N95: Бухгалтер 1С | O95: k.dzhumaev | P95: Списание есть в ETM и продажа в реестре, но в 1С нет реализации по этим билетам — счёт не выставлен | Q95: 57083566,57083603
A96: G03393 | B96: SkyWay Travel | C96: 2552668076 | D96: Сумма не сходится | E96: 1С | F96: A | G96: -45744.36 | H96: -8072.54 | I96: 8072.535 | J96: -53816.9 | K96: 46041.521 | L96: 46069 | N96: Бухгалтер 1С | O96: a.toktosunova|k.dzhumaev | P96: Реестр (8,072.54) совпадает с ETM (8,072.54), а в 1С -45,744.36: неверная сумма в 1С | Q96: 57038321,57092750
A97: G10910 | B97: ОсОО Ала-Арча Авиа | C97: 2416942418 | D97: Есть в ETM, нет в 1С | E97: 1С | F97: A | G97: 0 | H97: -53759.75 | I97: 53759.75 | J97: -53759.75 | K97: 46151.697 | N97: Бухгалтер 1С | O97: e.satarov | P97: Списание есть в ETM и продажа в реестре, но в 1С нет реализации по этим билетам — счёт не выставлен | Q97: 57267506
A98: G01054 | B98: Karakol Express | C98: 2416941473 | D98: Есть в ETM, нет в 1С | E98: 1С | F98: A | G98: 0 | H98: -53563.37 | J98: -53563.37 | K98: 46190.543 | N98: Бухгалтер 1С | P98: Списание есть в ETM, но в 1С нет реализации по этим билетам — счёт не выставлен | Q98: 57375328
A99: G03885 | B99: Steppe Travel | C99: 2559102087 | D99: Есть в ETM, нет в 1С | E99: 1С | F99: A | G99: 0 | H99: -53405.33 | I99: 53405.325 | J99: -53405.33 | K99: 46030.446 | N99: Бухгалтер 1С | O99: n.abdyldaeva | P99: Списание есть в ETM и продажа в реестре, но в 1С нет реализации по этим билетам — счёт не выставлен | Q99: 57014770
A100: G07527 | B100: Жолчу кызы А. | C100: 2461884042|2461884043|2461884045 | D100: Сумма не сходится | E100: 1С | F100: A | G100: 59142 | H100: -5914.2 | I100: 5914.2 | J100: 53227.8 | K100: 46160.6 | L100: 46160 | N100: Бухгалтер 1С | O100: k.dzhumaev | P100: Реестр (5,914.20) совпадает с ETM (5,914.20), а в 1С 59,142.00: неверная сумма в 1С | Q100: 57295759,57295717,57295753,57385347
...

Sheet Платежи
A1: Платежи: оплаты ETM без поступления в 1С и поступления 1С без оплаты в ETM
A3: Субагент | B3: Дата | C3: Где найдено | D3: Документ/ID | E3: Сумма | F3: Тип | G3: Источник | H3: Уверенность | I3: Что произошло | J3: Влияние на разрыв
A4: Джолдош уулу Руслан | B4: 46136 | C4: 1C | D4: Поступление на р/с, п/п ЦБ-С000203 | E4: 706600 | F4: PAYMENT_NOT_IN_ETM | G4: Бот ETM | H4: B | I4: Поступление 706,600.00 есть в 1С, зачисления на баланс ETM нет | J4: -706600
A5: Issyk-Kul Air | B5: 46207 | C5: 1C | D5: Поступление на р/с, п/п ЦБ-С000536 | E5: 698600 | F5: PAYMENT_NOT_IN_ETM | G5: Бот ETM | H5: B | I5: Поступление 698,600.00 есть в 1С, зачисления на баланс ETM нет | J5: -698600
A6: Ak-Bulak Voyage | B6: 46109.455 | C6: ETM | D6: 57174246 | E6: 562800 | F6: REPEATED_CREDIT | G6: Бот ETM | H6: A | I6: Оплата на 562,800.00 повторно зачислена в ETM через 21.4 ч, в 1С поступление одно | J6: 562800
A7: Ыйык Тур | B7: 46035.539 | C7: ETM | D7: 57021400 | E7: 529600 | F7: REPEATED_CREDIT | G7: Бот ETM | H7: A | I7: Оплата на 529,600.00 повторно зачислена в ETM через 23.7 ч, в 1С поступление одно | J7: 529600
A8: ИССЫК ТРИП | B8: 46065.559 | C8: ETM | D8: 57086445 | E8: 525900 | F8: ETM_PAYMENT_IN_MISSING_ACT_MONTH | G8: Выгрузка 1С | H8: B | I8: Оплата есть в ETM, акт 1С за месяц не выгружен | J8: 525900
A9: Ыйык Тур | B9: 46080 | C9: 1C | D9: Поступление на р/с, п/п ЦБ-С000298 | E9: 506000 | F9: PAYMENT_NOT_IN_ETM | G9: Бот ETM | H9: B | I9: Поступление 506,000.00 есть в 1С, зачисления на баланс ETM нет | J9: -506000
A10: Sunrise Tours | B10: 46092 | C10: 1C | D10: Поступление на р/с, п/п ЦБ-С001532 | E10: 501500 | F10: PAYMENT_NOT_IN_ETM | G10: Бот ETM | H10: B | I10: Поступление 501,500.00 есть в 1С, зачисления на баланс ETM нет | J10: -501500
A11: SkyWay Travel | B11: 46178 | C11: 1C | D11: Поступление на р/с, п/п ЦБ-С001264 | E11: 495300 | F11: PAYMENT_NOT_IN_ETM | G11: Бот ETM | H11: B | I11: Поступление 495,300.00 есть в 1С, зачисления на баланс ETM нет | J11: -495300
A12: Абдыраманова Д. А. | B12: 46173 | C12: 1C | D12: Поступление на р/с, п/п ЦБ-С001306 | E12: 493600 | F12: PAYMENT_NOT_IN_ETM | G12: Бот ETM | H12: B | I12: Поступление 493,600.00 есть в 1С, зачисления на баланс ETM нет | J12: -493600
A13: Осмонова А. Н. | B13: 46160 | C13: 1C | D13: Поступление на р/с, п/п ЦБ-С002359 | E13: 493300 | F13: PAYMENT_NOT_IN_ETM | G13: Бот ETM | H13: B | I13: Поступление 493,300.00 есть в 1С, зачисления на баланс ETM нет | J13: -493300
A14: SkyWay Travel | B14: 46165 | C14: 1C | D14: Поступление на р/с, п/п ЦБ-С001221 | E14: 487700 | F14: PAYMENT_NOT_IN_ETM | G14: Бот ETM | H14: B | I14: Поступление 487,700.00 есть в 1С, зачисления на баланс ETM нет | J14: -487700
A15: Ак-Куу Авиа | B15: 46104 | C15: 1C | D15: Поступление на р/с, п/п ЦБ-С002034 | E15: 486900 | F15: PAYMENT_NOT_IN_ETM | G15: Бот ETM | H15: B | I15: Поступление 486,900.00 есть в 1С, зачисления на баланс ETM нет | J15: -486900
... A331: Чынарова Бурул Джолдошовна | B331: 46148 | C331: 1C | D331: Поступление на р/с, п/п ЦБ-С000048 | E331: 95000 | F331: PAYMENT_NOT_IN_ETM | G331: Бот ETM | H331: B | I331: Поступление 95,000.00 есть в 1С, зачисления на баланс ETM нет | J331: -95000

Sheet Аномалии
A1: Повторные операции и аномалии (67 шт.)
A3: Тип | B3: Субагент | C3: Билеты/документ | D3: Дата | E3: Сумма, KGS | F3: Описание
A4: Повторная оплата | B4: Ak-Bulak Voyage | C4: 57174246 | D4: 46109.455 | E4: 562800 | F4: Оплата на 562,800.00 повторно зачислена в ETM через 21.4 ч, в 1С поступление одно
A5: Повторная оплата | B5: Ыйык Тур | C5: 57021400 | D5: 46035.539 | E5: 529600 | F5: Оплата на 529,600.00 повторно зачислена в ETM через 23.7 ч, в 1С поступление одно
A6: Повторная оплата | B6: SkyWay Travel | C6: 57419271 | D6: 46206.614 | E6: 410800 | F6: Оплата на 410,800.00 повторно зачислена в ETM через 30.7 ч, в 1С поступление одно
A7: Повторная оплата | B7: ИП Бейшенова Д. О. | C7: 57117017 | D7: 46083.768 | E7: 388600 | F7: Оплата на 388,600.00 повторно зачислена в ETM через 8.1 ч, в 1С поступление одно
A8: Повторная оплата | B8: Сатар уулу Санжар | C8: 57493417 | D8: 46232.703 | E8: 375900 | F8: Оплата на 375,900.00 повторно зачислена в ETM через 29.0 ч, в 1С поступление одно
A9: Повторная оплата | B9: Ак-Куу Авиа | C9: 57070163 | D9: 46056.802 | E9: 365100 | F9: Оплата на 365,100.00 повторно зачислена в ETM через 3.1 ч, в 1С поступление одно
A10: Повторная оплата | B10: ИССЫК ТРИП | C10: 57300423 | D10: 46162.64 | E10: 347500 | F10: Оплата на 347,500.00 повторно зачислена в ETM через 5.7 ч, в 1С поступление одно
A11: Повторная оплата | B11: ЧОЛПОН ЭЙР | C11: 57278297 | D11: 46155.795 | E11: 335700 | F11: Оплата на 335,700.00 повторно зачислена в ETM через 10.0 ч, в 1С поступление одно
A12: Повторная оплата | B12: Абдылда уулу Б. | C12: 57075810 | D12: 46060.68 | E12: 331500 | F12: Оплата на 331,500.00 повторно зачислена в ETM через 23.8 ч, в 1С поступление одно
A13: Повторная оплата | B13: Тянь-Шань Тур | C13: 57433087 | D13: 46210.626 | E13: 288600 | F13: Оплата на 288,600.00 повторно зачислена в ETM через 22.2 ч, в 1С поступление одно
A14: Повторная оплата | B14: Жибек Эйр | C14: 57042021 | D14: 46044.673 | E14: 249400 | F14: Оплата на 249,400.00 повторно зачислена в ETM через 29.7 ч, в 1С поступление одно
A15: Повторная оплата | B15: Ыйык Тур | C15: 57240708 | D15: 46144.368 | E15: 245400 | F15: Оплата на 245,400.00 повторно зачислена в ETM через 21.2 ч, в 1С поступление одно
... A70: Двойное списание | B70: SkyWay Travel | C70: 2460735648 | D70: 46212.416 | E70: -10287 | F70: В ETM 1 лишн. списание(й) одного билета на 10,287.00; без дубля сумма совпадает с 1С

Sheet 1С разрывы между актами
A1: 1С: непрерывность сальдо между актами
A2: Повторяющиеся суммы у разных субагентов (107 557,10; 283 308,99 …) — вопрос бухгалтеру: пакетная корректировка?
A3: Субагент | B3: Период | C3: Конечное сальдо пред. акта | D3: Начальное сальдо акта | E3: Скачок | F3: Тип
A4: ИССЫК ТРИП | B4: 2026-03 | C4: -572828.38 | D4: -2851740.3 | E4: -2278911.9 | F4: Через пропущенный месяц — акт не выгружен
A5: Сатар уулу Санжар | B5: 2026-05 | C5: 202649.34 | D5: -1110441.9 | E5: -1313091.3 | F5: Через пропущенный месяц — акт не выгружен
A6: Чынар уулу Эмир | B6: 2026-04 | C6: -50955.04 | D6: -1242772.6 | E6: -1191817.6 | F6: Через пропущенный месяц — акт не выгружен
A7: ИП Токтосун кызы Н. | B7: 2026-03 | C7: -158891.43 | D7: 828216.58 | E7: 987108.01 | F7: Через пропущенный месяц — акт не выгружен
A8: Жибек Эйр | B8: 2026-06 | C8: -2196501.1 | D8: -1316554.8 | E8: 879946.38 | F8: Через пропущенный месяц — акт не выгружен
A9: Сатар уулу Санжар | B9: 2026-07 | C9: -1806698.6 | D9: -2490873.4 | E9: -684174.86 | F9: Через пропущенный месяц — акт не выгружен
A10: МУРАС ТРИП | B10: 2026-07 | C10: -119011.97 | D10: 475446.34 | E10: 594458.31 | F10: Через пропущенный месяц — акт не выгружен
A11: Жолчу кызы А. | B11: 2026-07 | C11: -534280.46 | D11: -1125552.1 | E11: -591271.65 | F11: Через пропущенный месяц — акт не выгружен
A12: Ak-Bulak Voyage | B12: 2026-03 | C12: -398788.25 | D12: 102299.63 | E12: 501087.88 | F12: Через пропущенный месяц — акт не выгружен
A13: Тянь-Шань Тур | B13: 2026-06 | C13: -181558.58 | D13: -682561.67 | E13: -501003.09 | F13: Через пропущенный месяц — акт не выгружен
A14: ИП Муратов Э. У. | B14: 2026-04 | C14: -1595585.3 | D14: -1902113.1 | E14: -306527.79 | F14: Через пропущенный месяц — акт не выгружен
A15: Жибек Вояж | B15: 2026-05 | C15: -197796.96 | D15: 106851.1 | E15: 304648.06 | F15: Через пропущенный месяц — акт не выгружен
... A42: Sunrise Tours | B42: 2026-06 | C42: -1089093 | D42: -1088830 | E42: 263 | F42: Разрыв (месяцы подряд) — ошибка 1С

Sheet 1С нет актов
A1: Субагент-месяцы без акта 1С (из-за них часть сверки невозможна)
A3: Субагент | B3: Месяц
A4: Ak-Bulak Voyage | B4: 2026-02
A5: Асанов Кубат Чынаревич | B5: 2026-02
A6: Жибек Вояж | B6: 2026-04
A7: Жибек Эйр | B7: 2026-04
A8: Жибек Эйр | B8: 2026-05
A9: Жолчу кызы А. | B9: 2026-06
A10: ИП Асанов К. Б. | B10: 2026-02
A11: ИП Жумабекова Б. Н. | B11: 2026-05
A12: ИП Муратов Э. У. | B12: 2026-03
A13: ИП Токтосун кызы Н. | B13: 2026-02
A14: ИССЫК ТРИП | B14: 2026-02
... A27: Чынар уулу Эмир | B27: 2026-03

Sheet 1С черновик и переиздан
A1: Версии актов: используется последняя (переиздан); ниже — чем версии различаются
A2: Каждая версия по отдельности арифметически сходится; склеивать их нельзя — это и давало ложные «нарушения целостности».
A3: Папка 1С | B3: Период | C3: Сальдо конец (черновик) | D3: Сальдо конец (переиздан) | E3: Разница сальдо | F3: Строк (черновик) | G3: Строк (переиздан) | H3: Только в переизданном | I3: Только в черновике | J3: Проверка арифметики (черновик) | K3: Проверка арифметики (переиздан)
A4: Jailoo Trip | B4: 2026-05 | C4: 703791.61 | D4: 726777.55 | E4: 22985.94 | F4: 14 | G4: 15 | H4: 1 | I4: 0 | J4: -1.1641532e-10 | K4: 0
A5: Tengri Trip | B5: 2026-04 | C5: 586096.79 | D5: 606075.79 | E5: 19979 | F5: 29 | G5: 30 | H5: 1 | I5: 0 | J5: 1.1641532e-10 | K5: 1.1641532e-10
A6: Джолдош уулу Эмир | B6: 2026-02 | C6: -1217910 | D6: -1373610 | E6: -155700 | F6: 21 | G6: 22 | H6: 1 | I6: 0 | J6: -2.3283064e-10 | K6: -2.3283064e-10
A7: ИП Абдылда уулу Б. | B7: 2026-02 | C7: -2377124.5 | D7: -2320420.7 | E7: 56703.81 | F7: 72 | G7: 73 | H7: 1 | I7: 0 | J7: 0 | K7: 0
A8: ИП Абдыраманова Д. А. | B8: 2026-05 | C8: -141203.7 | D8: -140903.7 | E8: 300 | F8: 13 | G8: 14 | H8: 1 | I8: 0 | J8: -2.910383e-11 | K8: -2.910383e-11
A9: ИП Абдыраманова Ж. Д. | B9: 2026-06 | C9: -502180.35 | D9: -489424.35 | E9: 12756 | F9: 17 | G9: 18 | H9: 1 | I9: 0 | J9: 5.8207661e-11 | K9: 5.8207661e-11
A10: ИП Осмонова А. Н. | B10: 2026-04 | C10: -705211.2 | D10: -695320.2 | E10: 9891 | F10: 12 | G10: 13 | H10: 1 | I10: 0 | J10: 0 | K10: 0
A11: Ниязбеков Кубат Таалайевич | B11: 2026-06 | C11: -393972.05 | D11: -343163.93 | E11: 50808.12 | F11: 18 | G11: 19 | H11: 1 | I11: 0 | J11: 0 | K11: 0
A12: ОсОО "Алтын Эйр" | B12: 2026-06 | C12: -1797428.3 | D12: -1754270.3 | E12: 43158 | F12: 35 | G12: 36 | H12: 1 | I12: 0 | J12: 0 | K12: -2.3283064e-10
A13: ОсОО "Иссык Тур" | B13: 2026-06 | C13: -446129.73 | D13: -414876.27 | E13: 31253.46 | F13: 27 | G13: 28 | H13: 1 | I13: 0 | J13: 1.1641532e-10 | K13: 1.1641532e-10
A14: ОсОО "Кок-Жайык Вояж" | B14: 2026-07 | C14: -74298.36 | D14: -55615.31 | E14: 18683.05 | F14: 36 | G14: 37 | H14: 1 | I14: 0 | J14: -1.4551915e-11 | K14: -5.8207661e-11
A15: ОсОО "Манас Тур" | B15: 2026-03 | C15: -980029.12 | D15: -962140.38 | E15: 17888.74 | F15: 13 | G15: 14 | H15: 1 | I15: 0 | J15: 0 | K15: 0
... A18: Эсенбек уулу Азамат | B18: 2026-02 | C18: 200859.12 | D18: 244493.31 | E18: 43634.19 | F18: 9 | G18: 10 | H18: 1 | I18: 0 | J18: 0 | K18: 0

Sheet Сотрудники реестра
A1: Ошибки записи в реестре по сотрудникам (продажи по субагентам)
A2: Различие значимо, только если p-value < 0.05. Если нет — честный вывод: концентрации ошибок по сотруднику в данных нет.
A3: Сотрудник | B3: Ошибок в реестре | C3: Продаж | D3: Доля ошибок | E3: 95% ДИ от | F3: 95% ДИ до | G3: p-value (хи-квадрат) | H3: Различие значимо?
A4: b.isakov | B4: 20 | C4: 1282 | D4: 0.015600624 | E4: 0.010121358 | F4: 0.023974288 | G4: 0.48960908 | H4: FALSE
A5: a.toktosunova | B5: 19 | C5: 1329 | D5: 0.014296464 | E5: 0.0091712945 | F5: 0.022221483 | G5: 0.48960908 | H5: FALSE
A6: g.omurbekova | B6: 15 | C6: 1282 | D6: 0.011700468 | E6: 0.0071032696 | F6: 0.019215369 | G6: 0.48960908 | H6: FALSE
A7: d.mambetova | B7: 15 | C7: 1359 | D7: 0.011037528 | E7: 0.0067001382 | F7: 0.018131508 | G7: 0.48960908 | H7: FALSE
A8: r.sydykov | B8: 14 | C8: 1375 | D8: 0.010181818 | E8: 0.0060746518 | F8: 0.017018356 | G8: 0.48960908 | H8: FALSE
A9: e.satarov | B9: 13 | C9: 1294 | D9: 0.010046368 | E9: 0.00588043 | F9: 0.017112823 | G9: 0.48960908 | H9: FALSE
A10: n.abdyldaeva | B10: 11 | C10: 1327 | D10: 0.0082893745 | E10: 0.0046348573 | F10: 0.01478263 | G10: 0.48960908 | H10: FALSE
A11: k.dzhumaev | B11: 10 | C11: 1334 | D11: 0.0074962519 | E11: 0.0040768317 | F11: 0.013744112 | G11: 0.48960908 | H11: FALSE

Sheet Модель
A1: ML: предупреждающая модель — предсказывает источник проблемы по операции ETM
A2: Метки получены правилами (слабая разметка), признаки известны на момент проводки, проверка строго по времени, дважды. Рядом с метриками — тривиальные baseline. Вывод: модель приоритизирует проверку, а не заменяет правила.
A3: Метрика | B3: main (last month) | C3: check (previous month)
A4: test_month | B4: 2026-07 | C4: 2026-06
A5: train_months | B5: 2026-01..2026-06 | C5: 2026-01..2026-05
A6: n_train | B6: 20067 | C6: 16065
A7: n_test | B7: 4451 | C7: 4002
A8: test_error_rate | B8: 0.065153898 | C8: 0.071464268
A9: accuracy | B9: 0.91889463 | C9: 0.91604198
A10: accuracy_majority_baseline | B10: 0.9348461 | C10: 0.92853573
A11: macro_f1 | B11: 0.2295023 | C11: 0.23673417
A12: macro_f1_majority_baseline | B12: 0.19326521 | C12: 0.19258875
A13: balanced_accuracy | B13: 0.22049423 | C13: 0.22586284
A14: any_error_pr_auc | B14: 0.10264268 | C14: 0.12238104
A15: any_error_pr_auc_baseline_prior_rate | B15: 0.072232017 | C15: 0.075291641
A16: any_error_pr_auc_random | B16: 0.065153898 | C16: 0.071464268
A17: any_error_roc_auc | B17: 0.55877897 | C17: 0.58285283
... A20: recall_at_top5pct | B20: 0.086206897 | C20: 0.090909091
A22: По классам (тест — последний месяц)
A23: class | B23: precision | C23: recall | D23: f1 | E23: support
A24: OK | B24: 0.93643873 | C24: 0.98077385 | D24: 0.95809367 | E24: 4161
A25: BOT | B25: 0.33333333 | C25: 0.083333333 | D25: 0.13333333 | E25: 60
A26: 1C | B26: 0.066666667 | C26: 0.026315789 | D26: 0.037735849 | E26: 114
A27: AGENT | B27: 0 | C27: 0 | D27: 0 | E27: 33
A28: REVIEW | B28: 0.038461538 | C28: 0.012048193 | D28: 0.018348624 | E28: 83
A30: Важность признаков (падение PR-AUC при перемешивании)
A31: feature | B31: pr_auc_drop_when_shuffled
A32: hours_since_same_payment | B32: 0.025557468
A33: kind | B33: 0.01704146
A34: agent_prior_n | B34: 0.005508854
A35: prior_same_ticket_rows | B35: 0.0027737964
A36: hour | B36: 0.0023504794
A37: employee | B37: 0.0018097045
A38: creator | B38: 0.0017313981
A39: weekday | B39: 0.0011145773
A40: n_tickets | B40: 0.0010175246
A41: month_end | B41: -3.1150857e-06
A42: currency | B42: -0.00038613088
A43: dom | B43: -0.0010952312
... A46: agent_prior_err_rate | B46: -0.016029482

Sheet Кейсы для защиты
A1: Три реальных случая: сумма → билет → где потерялось → кто проверяет → что исправить
A3: Кейс 1. Неверная сумма в 1С (подтверждена реестром)
A4: Субагент | B4: Aylana Tour
A5: Сумма и билет | B5: Билет 2461885523: ETM списал 91,284.00, реестр 91,284.00, а в 1С реализация на 19,284.00.
A6: Где потерялось | B6: Реестр и ETM совпадают, 1С одна отличается на 72,000.00 (Реализация AR DJDCDE).
A7: Кто проверяет | B7: Бухгалтер 1С; запись в реестре вёл b.isakov.
A8: Что исправить | B8: Исправить реализацию в 1С на +72,000.00; баланс ETM не трогать.
A10: Кейс 2. Бот списал билет дважды
A11: Субагент | B11: ТАЛАС ЛАЙН
A12: Сумма и билет | B12: Билет 2416946131: в ETM два одинаковых списания, лишнее 62,508.38.
A13: Где потерялось | B13: ETM-операции 57192041,57192059; без дубля сумма ETM = 1С (62,508.38).
A14: Кто проверяет | B14: Разработчик/поддержка бота ETM (защита от повторной проводки); менеджер субагента — возврат списания.
A15: Что исправить | B15: Вернуть на баланс ETM 62,508.38.
A17: Кейс 3. Оплата зачислена в ETM повторно
A18: Субагент | B18: Ak-Bulak Voyage
A19: Сумма и билет | B19: Оплата 562,800.00 от 28.03.2026: в ETM две одинаковые проводки, в 1С поступление одно.
A20: Где потерялось | B20: Оплата на 562,800.00 повторно зачислена в ETM через 21.4 ч, в 1С поступление одно
A21: Кто проверяет | B21: Разработчик/поддержка бота ETM; казначей (подтвердить, что деньги пришли один раз).
A22: Что исправить | B22: Списать с баланса ETM 562,800.00.

Sheet Вопросы бухгалтеру
A1: Конкретные вопросы, которые надо закрыть с бухгалтером
A3: № | B3: Вопрос | C3: Сколько случаев / KGS | D3: Как меняется результат, если ответ «да»
A4: 1 | B4: Сервисный сбор: проводится ли он в 1С отдельной строкой, а в ETM входит в сумму выкупа? Подтвердить, что суммы групп должны совпадать до копейки. | C4: 758 групп с остатком | D4: Группы с остатком, кратным сбору, перейдут из «проверка» в «норма»
A5: 2 | B5: Лаг между проводкой ETM и реализацией 1С: какой допустим (дни)? Операция на границе месяцев — ошибка или перенос? | C5: медиана лага OK-групп 0 дн.; 95-й процентиль 0 дн. | D5: Операции на стыке месяцев исключаются из «нет в 1С» / «акт не выгружен»
A6: 3 | B6: Повторяющиеся суммы разрыва сальдо 1С у разных субагентов (107 557,10; 283 308,99; 4 800; 27 500) — пакетная корректировка/сторно? | C6: 20 разрывов, 2,053,526.35 KGS | D6: Разрыв считается задокументированной корректировкой, а не ошибкой
A7: 4 | B7: Выгрузить недостающие акты 1С по перечню на листе «1С нет актов». | C7: 24 субагент-месяцев | D7: Снимает группы «акт не выгружен» и «скачок через пропуск»
A8: 5 | B8: Кто вводит сумму акта вручную и бывают ли опечатки? Как отличить их от ошибки субагента при самостоятельной выписке (нет записи в реестре)? | C8: 334 групп без третьего источника | D8: Часть «проверка» получит владельца ошибки
A9: 6 | B9: Начальный разрыв на 1 января: есть ли акт сверки/сальдо открытия, которое его объясняет? | C9: 36 субагентов, нетто 2,683,079.59 KGS | D9: Начальный разрыв уйдёт из «выяснить»
A10: 7 | B10: Поступления 1С, по которым в ETM нет оплаты: зачисляются ли такие оплаты на другой договор/в другой период или действительно не доходят на депозит? Номер ЦБ-С… не уникален между субагентами, поэтому как ключ не использован. | C10: 221 поступлений, 60,646,400.00 KGS | D10: Крупнейшая компонента разрыва; ответ определяет, кому её исправлять — боту или казначею

Sheet Допущения и проверки
A1: Допущения, проверки целостности и ограничения
A3: Пункт | B3: Значение / пояснение
A4: Версия акта | B4: Берётся последняя: переиздан > без статуса > черновик. Различия — на листе «1С черновик и переиздан».
A5: Единица сравнения | B5: Связная группа билетов внутри субагента (union-find по билетам ETM, 1С и реестра), а не строка к строке.
A6: Допуск | B6: 5 KGS для ETM↔1С (оба в сомах); 0,5% для реестра в валюте (курс реестра может отличаться).
A7: Баланс ETM | B7: balance_after — сквозной баланс субагента; цепочка проверяется по субагенту; одинаковая секунда — не потеря данных.
A8: Реестр | B8: Сумма разбирается с учётом разделителей (7.889,70 → 7889.70) и курсов строки; номер билета в колонке суммы помечается отдельно.
A9: Корпоративные клиенты | B9: Стороны реестра без единого общего билета с субагентами считаются прямыми клиентами; баланс субагента они не затрагивают.
A10: Платежи | B10: Оплата ETM ↔ поступление 1С: тот же субагент, сумма ±1 KGS, дата ±7 дней, один к одному. Номера ЦБ-С… не уникальны между субагентами и ключом не служат.
A11: Корректировки | B11: Сторона правки определяется источником: 1С → правка 1С; бот/ETM → правка баланса ETM; реестр → баланс не меняется; остальное → «выяснить».
A12: Ограничение | B12: Билеты, выписанные субагентом самостоятельно, не попадают в реестр, поэтому для них источник ошибки в сумме определяется только по формальным признакам.
A13: — проверки целостности (значения из прогона) —
A14: ticket_agent_conflicts | B14: 0
A15: etm_rows_outside_window | B15: 0
A16: etm_chain_breaks_agent_level | B16: 6
A17: etm_chain_breaks_agents | B17: 2
A18: etm_chain_total_mismatch_agents | B18: 0
A19: etm_rows_without_ticket_not_payment | B19: 0
A20: 1c_rows_without_ticket_not_receipt | B20: 0
A21: registry_rows_unassigned_agent | B21: 1
A22: bridge_max_abs_unexplained | B22: 2.2118911147117615e-09
A23: monthly_identity_max_abs | B23: 1.1641532182693481e-09
A24: actions_max_abs_check | B24: 6.984919309616089e-10
